---
layout:     post
title:      æ·±å…¥è§£æâ€œJava å­—èŠ‚ç  â€ ä¹‹ ã€Œä»æ¡ˆä¾‹æ·±åº¦è§£è¯» Java å­—èŠ‚ç ã€
subtitle:   
date:       2019-11-2
author:     tomaså®¶çš„å°æ‹¨æµªé¼“
header-img: img/post-bg-20191014-article1.jpg
catalog: true
tags:
    - Java
    - JVM
---
# æ·±å…¥è§£æâ€œJava å­—èŠ‚ç  â€ ä¹‹ ã€Œä»æ¡ˆä¾‹æ·±åº¦è§£è¯» Java å­—èŠ‚ç ã€


> æœ¬æ–‡ä¸»è¦æ˜¯ã€Šæ·±å…¥æ¢ç´¢ JVMã€‹ç³»åˆ—ä¸­ã€å­—èŠ‚ç ç¯‡ã€æ–‡ç« ï¼Œä¸»è¦é€šè¿‡æ¡ˆä¾‹åˆ†æçš„å½¢åŠ¿ï¼Œæ¥æ›´ç›´è§‚çš„è®¤è¯† Java å­—èŠ‚ç ã€‚ç³»åˆ—æ–‡ç« ç›®å½•è§ï¼š[ã€Š æ·±å…¥æ¢ç´¢ JVM ã€‹æ–‡é›†]()

<br>

**ã€å­—èŠ‚ç ã€ç¯‡æ–‡ç« æ¨èï¼š**   
[æ·±å…¥è§£æâ€œJava å­—èŠ‚ç  â€ ä¹‹ ã€Œç±»æ–‡ä»¶ç»“æ„ã€](https://linling1.github.io/programming_blog/2019/11/01/æ·±å…¥è§£æ-Java-å­—èŠ‚ç -ä¹‹-ç±»æ–‡ä»¶ç»“æ„/)  
[æ·±å…¥è§£æâ€œJava å­—èŠ‚ç  â€ ä¹‹ ã€Œä»æ¡ˆä¾‹æ·±åº¦è§£è¯» Java å­—èŠ‚ç ã€](https://linling1.github.io/programming_blog/2019/11/02/æ·±å…¥è§£æ-Java-å­—èŠ‚ç -ä¹‹-ä»æ¡ˆä¾‹æ·±åº¦è§£è¯»-Java-å­—èŠ‚ç /)  
æ·±å…¥è§£æâ€œJava å­—èŠ‚ç  â€ ä¹‹ ã€Œè¿›ä¸€æ­¥æ¢ç©¶ Java æ–¹æ³•çš„å­—èŠ‚ç å®ç°ã€  
æ·±å…¥è§£æâ€œJava å­—èŠ‚ç  â€ ä¹‹ ã€Œä»æ¡ˆä¾‹è§£è¯»è™šæ‹Ÿæœºå±æ€§è¡¨ã€  
æ·±å…¥è§£æâ€œJava å­—èŠ‚ç  â€ ä¹‹ ã€Œè™šæ‹Ÿæœºæœºå­—èŠ‚ç æ‰§è¡Œå¼•æ“ã€  
æ·±å…¥è§£æâ€œJava å­—èŠ‚ç  â€ ä¹‹ ã€ŒåŠ¨æ€ä»£ç†çš„å®ç°ã€  

<br>

## å®ä¾‹ä»£ç 

~~~java
public class MyTest2 {
    String str = "Welcome";

    private int x = 5;

    public static Integer in = 10;

    public static void main(String[] args) {
        MyTest2 myTest2 = new MyTest2();

        myTest2.setX(8);

        in = 20;
    }

    public void setX(int x) {
        this.x = x;
    }
}
~~~

~~~shell
# -p  -private             Show all classes and members
javap -verbose -p MyTest2
~~~
ğŸ‘† -p æ‰ä¼šæ˜¾ç¤ºç§æœ‰çš„æˆå‘˜(å±æ€§ã€æ–¹æ³•ã€ç±»ç­‰)çš„ä¿¡æ¯

~~~
âœ  main git:(master) javap -p -v com.bayern.shengsiyuan.jvm_lecture.bytecode.lesson13.MyTest2
Classfile /Users/hayashishaochie/Documents/IdeaWorkspace/shengshiyuanProject/jvm_lecture/build/classes/main/com/bayern/shengsiyuan/jvm_lecture/bytecode/lesson13/MyTest2.class
  Last modified 2019-9-1; size 903 bytes
  MD5 checksum 44a9abb1b347cded1f441fbc8e1b7a7a
  Compiled from "MyTest2.java"
public class com.bayern.shengsiyuan.jvm_lecture.bytecode.lesson13.MyTest2
  minor version: 0
  major version: 52
  flags: ACC_PUBLIC, ACC_SUPER
Constant pool:
   #1 = Methodref          #10.#34        // java/lang/Object."<init>":()V
   #2 = String             #35            // Welcome
   #3 = Fieldref           #5.#36         // com/bayern/shengsiyuan/jvm_lecture/bytecode/lesson13/MyTest2.str:Ljava/lang/String;
   #4 = Fieldref           #5.#37         // com/bayern/shengsiyuan/jvm_lecture/bytecode/lesson13/MyTest2.x:I
   #5 = Class              #38            // com/bayern/shengsiyuan/jvm_lecture/bytecode/lesson13/MyTest2
   #6 = Methodref          #5.#34         // com/bayern/shengsiyuan/jvm_lecture/bytecode/lesson13/MyTest2."<init>":()V
   #7 = Methodref          #5.#39         // com/bayern/shengsiyuan/jvm_lecture/bytecode/lesson13/MyTest2.setX:(I)V
   #8 = Methodref          #40.#41        // java/lang/Integer.valueOf:(I)Ljava/lang/Integer;
   #9 = Fieldref           #5.#42         // com/bayern/shengsiyuan/jvm_lecture/bytecode/lesson13/MyTest2.in:Ljava/lang/Integer;
  #10 = Class              #43            // java/lang/Object
  #11 = Utf8               str
  #12 = Utf8               Ljava/lang/String;
  #13 = Utf8               x
  #14 = Utf8               I
  #15 = Utf8               in
  #16 = Utf8               Ljava/lang/Integer;
  #17 = Utf8               <init>
  #18 = Utf8               ()V
  #19 = Utf8               Code
  #20 = Utf8               LineNumberTable
  #21 = Utf8               LocalVariableTable
  #22 = Utf8               this
  #23 = Utf8               Lcom/bayern/shengsiyuan/jvm_lecture/bytecode/lesson13/MyTest2;
  #24 = Utf8               main
  #25 = Utf8               ([Ljava/lang/String;)V
  #26 = Utf8               args
  #27 = Utf8               [Ljava/lang/String;
  #28 = Utf8               myTest2
  #29 = Utf8               setX
  #30 = Utf8               (I)V
  #31 = Utf8               <clinit>    // ç±»æ„é€ å™¨ï¼Œå¯¹ç±»çš„é™æ€å˜é‡ã€é™æ€ä»£ç å—è¿›è¡Œåˆå§‹åŒ–ï¼›å¦‚æœæ²¡æœ‰éœ€è¦åˆå§‹åŒ–çš„æ•°æ®ï¼Œåˆ™ä¸ä¼šæœ‰<clinit>æ–¹æ³•
  #32 = Utf8               SourceFile
  #33 = Utf8               MyTest2.java
  #34 = NameAndType        #17:#18        // "<init>":()V
  #35 = Utf8               Welcome
  #36 = NameAndType        #11:#12        // str:Ljava/lang/String;
  #37 = NameAndType        #13:#14        // x:I
  #38 = Utf8               com/bayern/shengsiyuan/jvm_lecture/bytecode/lesson13/MyTest2
  #39 = NameAndType        #29:#30        // setX:(I)V
  #40 = Class              #44            // java/lang/Integer
  #41 = NameAndType        #45:#46        // valueOf:(I)Ljava/lang/Integer;
  #42 = NameAndType        #15:#16        // in:Ljava/lang/Integer;
  #43 = Utf8               java/lang/Object
  #44 = Utf8               java/lang/Integer
  #45 = Utf8               valueOf
  #46 = Utf8               (I)Ljava/lang/Integer;
{
  java.lang.String str;
    descriptor: Ljava/lang/String;
    flags:

  private int x;
    descriptor: I
    flags: ACC_PRIVATE

  public static java.lang.Integer in;
    descriptor: Ljava/lang/Integer;
    flags: ACC_PUBLIC, ACC_STATIC

  public com.bayern.shengsiyuan.jvm_lecture.bytecode.lesson13.MyTest2();
    descriptor: ()V
    flags: ACC_PUBLIC
    Code:
      stack=2, locals=1, args_size=1
         0: aload_0
         1: invokespecial #1                  // Method java/lang/Object."<init>":()V
         4: aload_0
         5: ldc           #2                  // String Welcome
         7: putfield      #3                  // Field str:Ljava/lang/String;
        10: aload_0
        11: iconst_5
        12: putfield      #4                  // Field x:I
        15: return
      LineNumberTable:
        line 3: 0
        line 4: 4
        line 6: 10
      LocalVariableTable:
        Start  Length  Slot  Name   Signature
            0      16     0  this   Lcom/bayern/shengsiyuan/jvm_lecture/bytecode/lesson13/MyTest2;

  public static void main(java.lang.String[]);
    descriptor: ([Ljava/lang/String;)V
    flags: ACC_PUBLIC, ACC_STATIC
    Code:
      stack=2, locals=2, args_size=1
         0: new           #5                  // class com/bayern/shengsiyuan/jvm_lecture/bytecode/lesson13/MyTest2
         3: dup
         4: invokespecial #6                  // Method "<init>":()V
         7: astore_1
         8: aload_1
         9: bipush        8
        11: invokevirtual #7                  // Method setX:(I)V
        14: bipush        20
        16: invokestatic  #8                  // Method java/lang/Integer.valueOf:(I)Ljava/lang/Integer;  è‡ªåŠ¨è£…ç®±çš„è¿‡ç¨‹ï¼›å¯¹åº”æºç ã€Œin = 20;ã€
        19: putstatic     #9                  // Field in:Ljava/lang/Integer;
        22: return
      LineNumberTable:
        line 11: 0
        line 13: 8
        line 15: 14
        line 16: 22
      LocalVariableTable:
        Start  Length  Slot  Name   Signature
            0      23     0  args   [Ljava/lang/String;
            8      15     1 myTest2   Lcom/bayern/shengsiyuan/jvm_lecture/bytecode/lesson13/MyTest2;

  public void setX(int);
    descriptor: (I)V
    flags: ACC_PUBLIC
    Code:
      stack=2, locals=2, args_size=2
         0: aload_0
         1: iload_1
         2: putfield      #4                  // Field x:I
         5: return
      LineNumberTable:
        line 19: 0
        line 20: 5
      LocalVariableTable:
        Start  Length  Slot  Name   Signature
            0       6     0  this   Lcom/bayern/shengsiyuan/jvm_lecture/bytecode/lesson13/MyTest2;
            0       6     1     x   I

  static {};
    descriptor: ()V
    flags: ACC_STATIC
    Code:
      stack=1, locals=0, args_size=0
         0: bipush        10
         2: invokestatic  #8                  // Method java/lang/Integer.valueOf:(I)Ljava/lang/Integer;
         5: putstatic     #9                  // Field in:Ljava/lang/Integer;
         8: return
      LineNumberTable:
        line 8: 0
}
SourceFile: "MyTest2.java"

~~~

<br>

åå…­è¿›åˆ¶å­—èŠ‚ç   

~~~
CAFE BABE 0000 0034 002F 0A00 0A00 2208 0023 0900 0500 2409 0005 0025 0700 260A 0005 0022 0A00 0500 270A 0028 0029 0900 0500 2A07 002B 0100 0373 7472 0100 124C 6A61 7661 2F6C 616E 672F 5374 7269 6E67 3B01 0001 7801 0001 4901 0002 696E 0100 134C 6A61 7661 2F6C 616E 672F 496E 7465 6765 723B 0100 063C 696E 6974 3E01 0003 2829 5601 0004 436F 6465 0100 0F4C 696E 654E 756D 6265 7254 6162 6C65 0100 124C 6F63 616C 5661 7269 6162 6C65 5461 626C 6501 0004 7468 6973 0100 3E4C 636F 6D2F 6261 7965 726E 2F73 6865 6E67 7369 7975 616E 2F6A 766D 5F6C 6563 7475 7265 2F62 7974 6563 6F64 652F 6C65 7373 6F6E 3133 2F4D 7954 6573 7432 3B01 0004 6D61 696E 0100 1628 5B4C 6A61 7661 2F6C 616E 672F 5374 7269 6E67 3B29 5601 0004 6172 6773 0100 135B 4C6A 6176 612F 6C61 6E67 2F53 7472 696E 673B 0100 076D 7954 6573 7432 0100 0473 6574 5801 0004 2849 2956 0100 083C 636C 696E 6974 3E01 000A 536F 7572 6365 4669 6C65 0100 0C4D 7954 6573 7432 2E6A 6176 610C 0011 0012 0100 0757 656C 636F 6D65 0C00 0B00 0C0C 000D 000E 0100 3C63 6F6D 2F62 6179 6572 6E2F 7368 656E 6773 6979 7561 6E2F 6A76 6D5F 6C65 6374 7572 652F 6279 7465 636F 6465 2F6C 6573 736F 6E31 332F 4D79 5465 7374 320C 001D 001E 0700 2C0C 002D 002E 0C00 0F00 1001 0010 6A61 7661 2F6C 616E 672F 4F62 6A65 6374 0100 116A 6176 612F 6C61 6E67 2F49 6E74 6567 6572 0100 0776 616C 7565 4F66 0100 1628 4929 4C6A 6176 612F 6C61 6E67 2F49 6E74 6567 6572 3B00 2100 0500 0A00 0000 0300 0000 0B00 0C00 0000 0200 0D00 0E00 0000 0900 0F00 1000 0000 0400 0100 1100 1200 0100 1300 0000 4200 0200 0100 0000 102A B700 012A 1202 B500 032A 08B5 0004 B100 0000 0200 1400 0000 0E00 0300 0000 0300 0400 0400 0A00 0600 1500 0000 0C00 0100 0000 1000 1600 1700 0000 0900 1800 1900 0100 1300 0000 5700 0200 0200 0000 17BB 0005 59B7 0006 4C2B 1008 B600 0710 14B8 0008 B300 09B1 0000 0002 0014 0000 0012 0004 0000 000B 0008 000D 000E 000F 0016 0010 0015 0000 0016 0002 0000 0017 001A 001B 0000 0008 000F 001C 0017 0001 0001 001D 001E 0001 0013 0000 003E 0002 0002 0000 0006 2A1B B500 04B1 0000 0002 0014 0000 000A 0002 0000 0013 0005 0014 0015 0000 0016 0002 0000 0006 0016 0017 0000 0000 0006 000D 000E 0001 0008 001F 0012 0001 0013 0000 0021 0001 0000 0000 0009 100A B800 08B3 0009 B100 0000 0100 1400 0000 0600 0100 0000 0800 0100 2000 0000 0200 21
~~~

<br>

### ä¸€ï¼Œmagic â€”â€”â€” é­”æ•°
æ ¼å¼ï¼š

~~~
u4    magic;
~~~

å†…å®¹ï¼š

~~~
CAFE BABE
~~~

<br>

### äºŒï¼Œç‰ˆæœ¬å·

#### 2.1 minor_version â€”â€”â€” æ¬¡ç‰ˆæœ¬å·  
æ ¼å¼ï¼š

~~~
u2    minor_version
~~~

å†…å®¹ï¼š

~~~
0000        // æ¬¡ç‰ˆæœ¬å·ï¼š0
~~~
<br>

#### 2.2 major_version â€”â€”â€”â€” ä¸»ç‰ˆæœ¬å·  
æ ¼å¼ï¼š  

~~~
u2    major_version
~~~

å†…å®¹ï¼š

~~~
0034        // ä¸»ç‰ˆæœ¬å·ï¼š0x34 -> 52(åè¿›åˆ¶) â€”â€”â€”â€” 52 â€”â€” jdk8
~~~
	
<br>

### ä¸‰ï¼Œå¸¸é‡æ± 

#### 3.1 constant_pool_count â€”â€”â€”â€” å¸¸é‡ä¸ªæ•°  
æ ¼å¼ï¼š

~~~
u2    constant_pool_count
~~~
	
å†…å®¹ï¼š
	
~~~
00 2F        // å¸¸é‡ä¸ªæ•°ï¼š0x002F -> 47(åè¿›åˆ¶) â€”â€”â€”â€” 47 ä¸ªå¸¸é‡
~~~

<br>

#### 3.2 constant_pool â€”â€”â€”â€” å¸¸é‡è¡¨

æ ¼å¼ï¼š  

~~~
cp_info    constant_pool[constant_pool_count - 1];    // cp_info æ•°ç»„çš„ä¸ªæ•°ä¸º 46 
~~~

<br>

* ç¬¬ä¸€ä¸ªå¸¸é‡  

~~~
# ç»“æ„
CONSTANT_Methodref_info {
    u1    tag
    u2    index        // æŒ‡å‘å£°æ˜æ–¹æ³•çš„ç±»æè¿°ç¦ CONSTANT_Class_info çš„ç´¢å¼•å€¼
    u2    index        // æŒ‡å‘åç§°åŠç±»å‹æè¿°ç¬¦ CONSTANT_NameAndType_info çš„ç´¢å¼•é¡¹
}
~~~

~~~
0A â€”â€”â€”â€” CONSTANT_Methodref_info
00 0A â€”â€”â€”â€” CONSTANT_Class_info ç´¢å¼• ï¼š10
00 22 â€”â€”â€”â€” CONSTANT_NameAndType_info ï¼š34
#1 = Methodref          #10.#34        // java/lang/Object."<init>":()V
~~~


* ç¬¬äºŒä¸ªå¸¸é‡  

~~~
# ç»“æ„
CONSTANT_String_info {
    u1    tag
    u2    index    // æŒ‡å‘å­—ç¬¦ä¸²å­—é¢é‡çš„ç´¢å¼•
}
~~~

~~~
08 â€”â€”â€”â€” CONSTANT_String_info
00 23 â€”â€”â€”â€” æŒ‡å‘å­—ç¬¦ä¸²å­—é¢é‡çš„ç´¢å¼•ï¼š35
#2 = String             #35            // Welcome
~~~

* ç¬¬ä¸‰ä¸ªå¸¸é‡

~~~
# ç»“æ„
CONSTANT_Fieldref_info {
    u1    tag
    u2    index    // æŒ‡å‘å£°æ˜å­—æ®µçš„ç±»æˆ–æ¥å£æè¿°ç¬¦ CONSTANT_Class_info çš„ç´¢å¼•é¡¹
    u2    index    // æŒ‡å‘å­—æ®µæè¿°ç¬¦ CONSTANT_NameAndType_info çš„ç´¢å¼•é¡¹
}
~~~

~~~
09 â€”â€”â€”â€” CONSTANT_Fieldref_info
00 05 â€”â€”â€”â€” CONSTANT_Class_info çš„ç´¢å¼•é¡¹ï¼š5
00 24 â€”â€”â€”â€” CONSTANT_NameAndType_info çš„ç´¢å¼•é¡¹ï¼š36
#3 = Fieldref           #5.#36         // com/bayern/shengsiyuan/jvm_lecture/bytecode/lesson13/MyTest2.str:Ljava/lang/String;
~~~

* ç¬¬å››ä¸ªå¸¸é‡

~~~
# ç»“æ„
CONSTANT_Fieldref_info {
    u1    tag
    u2    index    // æŒ‡å‘å£°æ˜å­—æ®µçš„ç±»æˆ–æ¥å£æè¿°ç¬¦ CONSTANT_Class_info çš„ç´¢å¼•é¡¹
    u2    index    // æŒ‡å‘å­—æ®µæè¿°ç¬¦ CONSTANT_NameAndType_info çš„ç´¢å¼•é¡¹
}
~~~

~~~
09 â€”â€”â€”â€” CONSTANT_Fieldref_info
00 05 â€”â€”â€”â€” CONSTANT_Class_info çš„ç´¢å¼•é¡¹ï¼š5
00 25 â€”â€”â€”â€” CONSTANT_NameAndType_info çš„ç´¢å¼•é¡¹ï¼š37
#4 = Fieldref           #5.#37         // com/bayern/shengsiyuan/jvm_lecture/bytecode/lesson13/MyTest2.x:I
~~~

* ç¬¬äº”ä¸ªå¸¸é‡

~~~
# ç»“æ„
CONSTANT_Class_info {
    u1    tag
    u2    index    // æŒ‡å‘å…¨é™å®šåå¸¸é‡é¡¹çš„ç´¢å¼•
}
~~~

~~~
07 â€”â€”â€”â€” CONSTANT_Class_info
00 26 â€”â€”â€”â€” å…¨é™å®šåå¸¸é‡é¡¹çš„ç´¢å¼•ï¼š38
#5 = Class              #38            // com/bayern/shengsiyuan/jvm_lecture/bytecode/lesson13/MyTest2
~~~

* ç¬¬å…­ä¸ªå¸¸é‡

~~~
# ç»“æ„
CONSTANT_Methodref_info {
    u1    tag
    u2    index        // æŒ‡å‘å£°æ˜æ–¹æ³•çš„ç±»æè¿°ç¦ CONSTANT_Class_info çš„ç´¢å¼•å€¼
    u2    index        // æŒ‡å‘åç§°åŠç±»å‹æè¿°ç¬¦ CONSTANT_NameAndType_info çš„ç´¢å¼•é¡¹
}
~~~

~~~
0A â€”â€”â€”â€” CONSTANT_Methodref_info
00 05 â€”â€”â€”â€” CONSTANT_Class_info çš„ç´¢å¼•å€¼ï¼š5
00 22 â€”â€”â€”â€” CONSTANT_NameAndType_info çš„ç´¢å¼•é¡¹ï¼š34
#6 = Methodref          #5.#34         // com/bayern/shengsiyuan/jvm_lecture/bytecode/lesson13/MyTest2."<init>":()V
~~~

* ç¬¬ä¸ƒä¸ªå¸¸é‡

~~~
# ç»“æ„
CONSTANT_Methodref_info {
    u1    tag
    u2    index        // æŒ‡å‘å£°æ˜æ–¹æ³•çš„ç±»æè¿°ç¦ CONSTANT_Class_info çš„ç´¢å¼•å€¼
    u2    index        // æŒ‡å‘åç§°åŠç±»å‹æè¿°ç¬¦ CONSTANT_NameAndType_info çš„ç´¢å¼•é¡¹
}
~~~

~~~
0A â€”â€”â€”â€” CONSTANT_Methodref_info
00 05 â€”â€”â€”â€” CONSTANT_Class_info çš„ç´¢å¼•å€¼ï¼š5
00 27 â€”â€”â€”â€” CONSTANT_NameAndType_info çš„ç´¢å¼•é¡¹ï¼š39
#7 = Methodref          #5.#39         // com/bayern/shengsiyuan/jvm_lecture/bytecode/lesson13/MyTest2.setX:(I)V
~~~

* ç¬¬å…«ä¸ªå¸¸é‡

~~~
# ç»“æ„
CONSTANT_Methodref_info {
    u1    tag
    u2    index        // æŒ‡å‘å£°æ˜æ–¹æ³•çš„ç±»æè¿°ç¦ CONSTANT_Class_info çš„ç´¢å¼•å€¼
    u2    index        // æŒ‡å‘åç§°åŠç±»å‹æè¿°ç¬¦ CONSTANT_NameAndType_info çš„ç´¢å¼•é¡¹
}
~~~

~~~
0A â€”â€”â€”â€” CONSTANT_Methodref_info
00 28 â€”â€”â€”â€” CONSTANT_Class_info çš„ç´¢å¼•å€¼ï¼š40
00 29 â€”â€”â€”â€” CONSTANT_NameAndType_info çš„ç´¢å¼•é¡¹ï¼š41
#8 = Methodref          #40.#41        // java/lang/Integer.valueOf:(I)Ljava/lang/Integer;
~~~

* ç¬¬ä¹ä¸ªå¸¸é‡

~~~
# ç»“æ„
CONSTANT_Fieldref_info {
    u1    tag
    u2    index    // æŒ‡å‘å£°æ˜å­—æ®µçš„ç±»æˆ–æ¥å£æè¿°ç¬¦ CONSTANT_Class_info çš„ç´¢å¼•é¡¹
    u2    index    // æŒ‡å‘å­—æ®µæè¿°ç¬¦ CONSTANT_NameAndType_info çš„ç´¢å¼•é¡¹
}
~~~

~~~
09 â€”â€”â€”â€” CONSTANT_Fieldref_info
00 05 â€”â€”â€”â€” CONSTANT_Class_info çš„ç´¢å¼•é¡¹ï¼š5
00 2A â€”â€”â€”â€” CONSTANT_NameAndType_info çš„ç´¢å¼•é¡¹ï¼š42
#9 = Fieldref           #5.#42         // com/bayern/shengsiyuan/jvm_lecture/bytecode/lesson13/MyTest2.in:Ljava/lang/Integer;
~~~

* ç¬¬åä¸ªå¸¸é‡

~~~
# ç»“æ„
CONSTANT_Class_info {
    u1    tag
    u2    index    // æŒ‡å‘å…¨é™å®šåå¸¸é‡é¡¹çš„ç´¢å¼•
}
~~~

~~~
07 â€”â€”â€”â€” CONSTANT_Class_info
00 2B â€”â€”â€”â€” å…¨é™å®šåå¸¸é‡é¡¹çš„ç´¢å¼•ï¼š43

#10 = Class              #43            // java/lang/Object
~~~

* ç¬¬åä¸€ä¸ªå¸¸é‡

~~~
# ç»“æ„
CONSTANT_Utf8_info {
    u1    tag
    u2    length       // UTF-8 ç¼–ç çš„å­—ç¬¦ä¸²é•¿åº¦
    u1    bytes        // é•¿åº¦ä¸º length çš„ UTF-8 ç¼–ç çš„å­—ç¬¦ä¸²
}
~~~

~~~
01 â€”â€”â€”â€” CONSTANT_Utf8_info
00 03 â€”â€”â€”â€” UTF-8 ç¼–ç çš„å­—ç¬¦ä¸²é•¿åº¦ï¼š3
73 74 72 â€”â€”â€”â€” str

#11 = Utf8               str
~~~

* ç¬¬åäºŒä¸ªå¸¸é‡

~~~
# ç»“æ„
CONSTANT_Utf8_info {
    u1    tag
    u2    length       // UTF-8 ç¼–ç çš„å­—ç¬¦ä¸²é•¿åº¦
    u1    bytes        // é•¿åº¦ä¸º length çš„ UTF-8 ç¼–ç çš„å­—ç¬¦ä¸²
}
~~~

~~~
01 â€”â€”â€”â€” CONSTANT_Utf8_info
00 12 â€”â€”â€”â€” UTF-8 ç¼–ç çš„å­—ç¬¦ä¸²é•¿åº¦ï¼š18
4C 6A 61 76 61 2F 6C 61 6E 67 2F 53 74 72 69 6E 67 3B â€”â€”â€”â€” Ljava/lang/String;

#12 = Utf8               Ljava/lang/String;
~~~

* ç¬¬åä¸‰ä¸ªå¸¸é‡

~~~
# ç»“æ„
CONSTANT_Utf8_info {
    u1    tag
    u2    length       // UTF-8 ç¼–ç çš„å­—ç¬¦ä¸²é•¿åº¦
    u1    bytes        // é•¿åº¦ä¸º length çš„ UTF-8 ç¼–ç çš„å­—ç¬¦ä¸²
}
~~~

~~~
01 â€”â€”â€”â€” CONSTANT_Utf8_info
00 01 â€”â€”â€”â€” UTF-8 ç¼–ç çš„å­—ç¬¦ä¸²é•¿åº¦ï¼š1
78 â€”â€”â€”â€” x

#13 = Utf8               x
~~~

* ç¬¬åå››ä¸ªå¸¸é‡

~~~
# ç»“æ„
CONSTANT_Utf8_info {
    u1    tag
    u2    length       // UTF-8 ç¼–ç çš„å­—ç¬¦ä¸²é•¿åº¦
    u1    bytes        // é•¿åº¦ä¸º length çš„ UTF-8 ç¼–ç çš„å­—ç¬¦ä¸²
}
~~~

~~~
01 â€”â€”â€”â€” CONSTANT_Utf8_info
00 01 â€”â€”â€”â€” UTF-8 ç¼–ç çš„å­—ç¬¦ä¸²é•¿åº¦ï¼š1
49 â€”â€”â€”â€” I

#14 = Utf8               I
~~~

* ç¬¬åäº”ä¸ªå¸¸é‡

~~~
# ç»“æ„
CONSTANT_Utf8_info {
    u1    tag
    u2    length       // UTF-8 ç¼–ç çš„å­—ç¬¦ä¸²é•¿åº¦
    u1    bytes        // é•¿åº¦ä¸º length çš„ UTF-8 ç¼–ç çš„å­—ç¬¦ä¸²
}
~~~

~~~
01 â€”â€”â€”â€” CONSTANT_Utf8_info
00 02 â€”â€”â€”â€” UTF-8 ç¼–ç çš„å­—ç¬¦ä¸²é•¿åº¦ï¼š2
69 6E â€”â€”â€”â€” in

#15 = Utf8               in
~~~

* ç¬¬åå…­ä¸ªå¸¸é‡

~~~
# ç»“æ„
CONSTANT_Utf8_info {
    u1    tag
    u2    length       // UTF-8 ç¼–ç çš„å­—ç¬¦ä¸²é•¿åº¦
    u1    bytes        // é•¿åº¦ä¸º length çš„ UTF-8 ç¼–ç çš„å­—ç¬¦ä¸²
}
~~~

~~~
01 â€”â€”â€”â€” CONSTANT_Utf8_info
00 13 â€”â€”â€”â€” UTF-8 ç¼–ç çš„å­—ç¬¦ä¸²é•¿åº¦ï¼š19
4C 6A 61 76 61 2F 6C 61 6E 67 2F 49 6E 74 65 67 65 72 3B â€”â€”â€”â€” Ljava/lang/Integer;

#16 = Utf8               Ljava/lang/Integer;
~~~

* ç¬¬åä¸ƒä¸ªå¸¸é‡

~~~
# ç»“æ„
CONSTANT_Utf8_info {
    u1    tag
    u2    length       // UTF-8 ç¼–ç çš„å­—ç¬¦ä¸²é•¿åº¦
    u1    bytes        // é•¿åº¦ä¸º length çš„ UTF-8 ç¼–ç çš„å­—ç¬¦ä¸²
}
~~~

~~~
01 â€”â€”â€”â€” CONSTANT_Utf8_info
00 06 â€”â€”â€”â€” UTF-8 ç¼–ç çš„å­—ç¬¦ä¸²é•¿åº¦ï¼š6
3C 69 6E 69 74 3E â€”â€”â€”â€” <init>

#17 = Utf8               <init>
~~~

* ç¬¬åå…«ä¸ªå¸¸é‡

~~~
# ç»“æ„
CONSTANT_Utf8_info {
    u1    tag
    u2    length       // UTF-8 ç¼–ç çš„å­—ç¬¦ä¸²é•¿åº¦
    u1    bytes        // é•¿åº¦ä¸º length çš„ UTF-8 ç¼–ç çš„å­—ç¬¦ä¸²
}
~~~

~~~
01 â€”â€”â€”â€” CONSTANT_Utf8_info
00 03 â€”â€”â€”â€” UTF-8 ç¼–ç çš„å­—ç¬¦ä¸²é•¿åº¦ï¼š3
28 29 56 â€”â€”â€”â€” ()V

#18 = Utf8               ()V
~~~

* ç¬¬åä¹ä¸ªå¸¸é‡

~~~
# ç»“æ„
CONSTANT_Utf8_info {
    u1    tag
    u2    length       // UTF-8 ç¼–ç çš„å­—ç¬¦ä¸²é•¿åº¦
    u1    bytes        // é•¿åº¦ä¸º length çš„ UTF-8 ç¼–ç çš„å­—ç¬¦ä¸²
}
~~~

~~~
01 â€”â€”â€”â€” CONSTANT_Utf8_info
00 04 â€”â€”â€”â€” UTF-8 ç¼–ç çš„å­—ç¬¦ä¸²é•¿åº¦ï¼š4
43 6F 64 65 â€”â€”â€”â€” Code

#19 = Utf8               Code
~~~

* ç¬¬äºŒåä¸ªå¸¸é‡

~~~
# ç»“æ„
CONSTANT_Utf8_info {
    u1    tag
    u2    length       // UTF-8 ç¼–ç çš„å­—ç¬¦ä¸²é•¿åº¦
    u1    bytes        // é•¿åº¦ä¸º length çš„ UTF-8 ç¼–ç çš„å­—ç¬¦ä¸²
}
~~~

~~~
01 â€”â€”â€”â€” CONSTANT_Utf8_info
00 0F â€”â€”â€”â€” UTF-8 ç¼–ç çš„å­—ç¬¦ä¸²é•¿åº¦ï¼š15
4C 69 6E 65 4E 75 6D 62 65 72 54 61 62 6C 65 â€”â€”â€”â€” LineNumberTable

#20 = Utf8               LineNumberTable
~~~

* ç¬¬äºŒåä¸€ä¸ªå¸¸é‡

~~~
# ç»“æ„
CONSTANT_Utf8_info {
    u1    tag
    u2    length       // UTF-8 ç¼–ç çš„å­—ç¬¦ä¸²é•¿åº¦
    u1    bytes        // é•¿åº¦ä¸º length çš„ UTF-8 ç¼–ç çš„å­—ç¬¦ä¸²
}
~~~

~~~
01 â€”â€”â€”â€” CONSTANT_Utf8_info
00 12 â€”â€”â€”â€” UTF-8 ç¼–ç çš„å­—ç¬¦ä¸²é•¿åº¦ï¼š18
4C 6F 63 61 6C 56 61 72 69 61 62 6C 65 54 61 62 6C 65 â€”â€”â€”â€” LocalVariableTable

#21 = Utf8               LocalVariableTable
~~~

* ç¬¬äºŒåäºŒä¸ªå¸¸é‡

~~~
# ç»“æ„
CONSTANT_Utf8_info {
    u1    tag
    u2    length       // UTF-8 ç¼–ç çš„å­—ç¬¦ä¸²é•¿åº¦
    u1    bytes        // é•¿åº¦ä¸º length çš„ UTF-8 ç¼–ç çš„å­—ç¬¦ä¸²
}
~~~

~~~
01 â€”â€”â€”â€” CONSTANT_Utf8_info 
00 04 â€”â€”â€”â€” UTF-8 ç¼–ç çš„å­—ç¬¦ä¸²é•¿åº¦ï¼š4
74 68 69 73 â€”â€”â€”â€” this

#22 = Utf8               this
~~~

* ç¬¬äºŒåä¸‰ä¸ªå¸¸é‡

~~~
# ç»“æ„
CONSTANT_Utf8_info {
    u1    tag
    u2    length       // UTF-8 ç¼–ç çš„å­—ç¬¦ä¸²é•¿åº¦
    u1    bytes        // é•¿åº¦ä¸º length çš„ UTF-8 ç¼–ç çš„å­—ç¬¦ä¸²
}
~~~

~~~
01 â€”â€”â€”â€” CONSTANT_Utf8_info 
00 3E â€”â€”â€”â€” UTF-8 ç¼–ç çš„å­—ç¬¦ä¸²é•¿åº¦ï¼š62
4C 63 6F 6D 2F 62 61 79 65 72 6E 2F 73 68 65 6E 67 73 69 79 75 61 6E 2F 6A 76 6D 5F 6C 65 63 74 75 72 65 2F 62 79 74 65 63 6F 64 65 2F 6C 65 73 73 6F 6E 31 33 2F 4D 79 54 65 73 74 32 3B â€”â€”â€”â€” Lcom/bayern/shengsiyuan/jvm_lecture/bytecode/lesson13/MyTest2;

#23 = Utf8               Lcom/bayern/shengsiyuan/jvm_lecture/bytecode/lesson13/MyTest2;
~~~

* ç¬¬äºŒåå››ä¸ªå¸¸é‡

~~~
# ç»“æ„
CONSTANT_Utf8_info {
    u1    tag
    u2    length       // UTF-8 ç¼–ç çš„å­—ç¬¦ä¸²é•¿åº¦
    u1    bytes        // é•¿åº¦ä¸º length çš„ UTF-8 ç¼–ç çš„å­—ç¬¦ä¸²
}
~~~

~~~
01 â€”â€”â€”â€” CONSTANT_Utf8_info
00 04 â€”â€”â€”â€” UTF-8 ç¼–ç çš„å­—ç¬¦ä¸²é•¿åº¦ï¼š4
6D 61 69 6E â€”â€”â€”â€” main

#24 = Utf8               main
~~~

* ç¬¬äºŒåäº”ä¸ªå¸¸é‡

~~~
# ç»“æ„
CONSTANT_Utf8_info {
    u1    tag
    u2    length       // UTF-8 ç¼–ç çš„å­—ç¬¦ä¸²é•¿åº¦
    u1    bytes        // é•¿åº¦ä¸º length çš„ UTF-8 ç¼–ç çš„å­—ç¬¦ä¸²
}
~~~

~~~
01 â€”â€”â€”â€” CONSTANT_Utf8_info
00 16 â€”â€”â€”â€” UTF-8 ç¼–ç çš„å­—ç¬¦ä¸²é•¿åº¦ï¼š22
28 5B 4C 6A 61 76 61 2F 6C 61 6E 67 2F 53 74 72 69 6E 67 3B 29 56 â€”â€”â€”â€” ([Ljava/lang/String;)V

#25 = Utf8               ([Ljava/lang/String;)V
~~~

* ç¬¬äºŒåå…­ä¸ªå¸¸é‡

~~~
# ç»“æ„
CONSTANT_Utf8_info {
    u1    tag
    u2    length       // UTF-8 ç¼–ç çš„å­—ç¬¦ä¸²é•¿åº¦
    u1    bytes        // é•¿åº¦ä¸º length çš„ UTF-8 ç¼–ç çš„å­—ç¬¦ä¸²
}
~~~

~~~
01 â€”â€”â€”â€” CONSTANT_Utf8_info
00 04 â€”â€”â€”â€” UTF-8 ç¼–ç çš„å­—ç¬¦ä¸²é•¿åº¦ï¼š4
61 72 67 73 â€”â€”â€”â€” args

#26 = Utf8               args
~~~

* ç¬¬äºŒåä¸ƒä¸ªå¸¸é‡

~~~
# ç»“æ„
CONSTANT_Utf8_info {
    u1    tag
    u2    length       // UTF-8 ç¼–ç çš„å­—ç¬¦ä¸²é•¿åº¦
    u1    bytes        // é•¿åº¦ä¸º length çš„ UTF-8 ç¼–ç çš„å­—ç¬¦ä¸²
}
~~~

~~~
01 â€”â€”â€”â€” CONSTANT_Utf8_info
00 13 â€”â€”â€”â€” UTF-8 ç¼–ç çš„å­—ç¬¦ä¸²é•¿åº¦ï¼š19
5B 4C 6A 61 76 61 2F 6C 61 6E 67 2F 53 74 72 69 6E 67 3B â€”â€”â€”â€” [Ljava/lang/String;

#27 = Utf8               [Ljava/lang/String;
~~~

* ç¬¬äºŒåå…«ä¸ªå¸¸é‡

~~~
# ç»“æ„
CONSTANT_Utf8_info {
    u1    tag
    u2    length       // UTF-8 ç¼–ç çš„å­—ç¬¦ä¸²é•¿åº¦
    u1    bytes        // é•¿åº¦ä¸º length çš„ UTF-8 ç¼–ç çš„å­—ç¬¦ä¸²
}
~~~

~~~
01 â€”â€”â€”â€” CONSTANT_Utf8_info
00 07 â€”â€”â€”â€” UTF-8 ç¼–ç çš„å­—ç¬¦ä¸²é•¿åº¦ï¼š7
6D 79 54 65 73 74 32 â€”â€”â€”â€” myTest2

#28 = Utf8               myTest2
~~~

* ç¬¬äºŒåä¹ä¸ªå¸¸é‡

~~~
# ç»“æ„
CONSTANT_Utf8_info {
    u1    tag
    u2    length       // UTF-8 ç¼–ç çš„å­—ç¬¦ä¸²é•¿åº¦
    u1    bytes        // é•¿åº¦ä¸º length çš„ UTF-8 ç¼–ç çš„å­—ç¬¦ä¸²
}
~~~

~~~
01 â€”â€”â€”â€” CONSTANT_Utf8_info
00 04 â€”â€”â€”â€” UTF-8 ç¼–ç çš„å­—ç¬¦ä¸²é•¿åº¦ï¼š4
73 65 74 58 â€”â€”â€”â€” setX

#29 = Utf8               setX
~~~

* ç¬¬ä¸‰åä¸ªå¸¸é‡

~~~
# ç»“æ„
CONSTANT_Utf8_info {
    u1    tag
    u2    length       // UTF-8 ç¼–ç çš„å­—ç¬¦ä¸²é•¿åº¦
    u1    bytes        // é•¿åº¦ä¸º length çš„ UTF-8 ç¼–ç çš„å­—ç¬¦ä¸²
}
~~~

~~~
01 â€”â€”â€”â€” CONSTANT_Utf8_info
00 04 â€”â€”â€”â€” UTF-8 ç¼–ç çš„å­—ç¬¦ä¸²é•¿åº¦ï¼š4
28 49 29 56 â€”â€”â€”â€” (I)V

#30 = Utf8               (I)V
~~~

* ç¬¬ä¸‰åä¸€ä¸ªå¸¸é‡

~~~
# ç»“æ„
CONSTANT_Utf8_info {
    u1    tag
    u2    length       // UTF-8 ç¼–ç çš„å­—ç¬¦ä¸²é•¿åº¦
    u1    bytes        // é•¿åº¦ä¸º length çš„ UTF-8 ç¼–ç çš„å­—ç¬¦ä¸²
}
~~~

~~~
01 â€”â€”â€”â€” CONSTANT_Utf8_info
00 08 â€”â€”â€”â€” UTF-8 ç¼–ç çš„å­—ç¬¦ä¸²é•¿åº¦ï¼š8
3C 63 6C 69 6E 69 74 3E â€”â€”â€”â€” <clinit>

#31 = Utf8               <clinit>
~~~

* ç¬¬ä¸‰åäºŒä¸ªå¸¸é‡

~~~
# ç»“æ„
CONSTANT_Utf8_info {
    u1    tag
    u2    length       // UTF-8 ç¼–ç çš„å­—ç¬¦ä¸²é•¿åº¦
    u1    bytes        // é•¿åº¦ä¸º length çš„ UTF-8 ç¼–ç çš„å­—ç¬¦ä¸²
}
~~~

~~~
01 â€”â€”â€”â€” CONSTANT_Utf8_info
00 0A â€”â€”â€”â€” UTF-8 ç¼–ç çš„å­—ç¬¦ä¸²é•¿åº¦ï¼š10
53 6F 75 72 63 65 46 69 6C 65 â€”â€”â€”â€” SourceFile

#32 = Utf8               SourceFile
~~~

* ç¬¬ä¸‰åä¸‰ä¸ªå¸¸é‡

~~~
# ç»“æ„
CONSTANT_Utf8_info {
    u1    tag
    u2    length       // UTF-8 ç¼–ç çš„å­—ç¬¦ä¸²é•¿åº¦
    u1    bytes        // é•¿åº¦ä¸º length çš„ UTF-8 ç¼–ç çš„å­—ç¬¦ä¸²
}
~~~

~~~
01 â€”â€”â€”â€” CONSTANT_Utf8_info
00 0C â€”â€”â€”â€” UTF-8 ç¼–ç çš„å­—ç¬¦ä¸²é•¿åº¦ï¼š12
4D 79 54 65 73 74 32 2E 6A 61 76 61 â€”â€”â€”â€” MyTest2.java

#33 = Utf8               MyTest2.java
~~~

* ç¬¬ä¸‰åå››ä¸ªå¸¸é‡

~~~
# ç»“æ„
CONSTANT_NameAndType_info {
    u1    tag        
    u2    index    // æŒ‡å‘è¯¥å­—æ®µæˆ–æ–¹æ³•åç§°å¸¸é‡é¡¹çš„ç´¢å¼•
    u2    index    // æŒ‡å‘è¯¥å­—æ®µæˆ–æ–¹æ³•æè¿°ç¬¦å¸¸é‡é¡¹çš„ç´¢å¼•
}
~~~

~~~
0C â€”â€”â€”â€” CONSTANT_NameAndType_info
00 11 â€”â€”â€”â€” è¯¥å­—æ®µæˆ–æ–¹æ³•åç§°å¸¸é‡é¡¹çš„ç´¢å¼•ï¼š17
00 12 â€”â€”â€”â€” è¯¥å­—æ®µæˆ–æ–¹æ³•æè¿°ç¬¦å¸¸é‡é¡¹çš„ç´¢å¼•ï¼š18

#34 = NameAndType        #17:#18        // "<init>":()V
~~~

* ç¬¬ä¸‰åäº”ä¸ªå¸¸é‡

~~~
# ç»“æ„
CONSTANT_Utf8_info {
    u1    tag
    u2    length       // UTF-8 ç¼–ç çš„å­—ç¬¦ä¸²é•¿åº¦
    u1    bytes        // é•¿åº¦ä¸º length çš„ UTF-8 ç¼–ç çš„å­—ç¬¦ä¸²
}
~~~

~~~
01 â€”â€”â€”â€” CONSTANT_Utf8_info
00 07 â€”â€”â€”â€” UTF-8 ç¼–ç çš„å­—ç¬¦ä¸²é•¿åº¦ï¼š7
57 65 6C 63 6F 6D 65 â€”â€”â€”â€” Welcome

#35 = Utf8               Welcome
~~~

* ç¬¬ä¸‰åå…­ä¸ªå¸¸é‡

~~~
# ç»“æ„
CONSTANT_NameAndType_info {
    u1    tag        
    u2    index    // æŒ‡å‘è¯¥å­—æ®µæˆ–æ–¹æ³•åç§°å¸¸é‡é¡¹çš„ç´¢å¼•
    u2    index    // æŒ‡å‘è¯¥å­—æ®µæˆ–æ–¹æ³•æè¿°ç¬¦å¸¸é‡é¡¹çš„ç´¢å¼•
}
~~~

~~~
0C â€”â€”â€”â€” CONSTANT_NameAndType_info
00 0B â€”â€”â€”â€” è¯¥å­—æ®µæˆ–æ–¹æ³•åç§°å¸¸é‡é¡¹çš„ç´¢å¼•ï¼š11
00 0C â€”â€”â€”â€” è¯¥å­—æ®µæˆ–æ–¹æ³•æè¿°ç¬¦å¸¸é‡é¡¹çš„ç´¢å¼•ï¼š12

#36 = NameAndType        #11:#12        // str:Ljava/lang/String;
~~~

* ç¬¬ä¸‰åä¸ƒä¸ªå¸¸é‡

~~~
# ç»“æ„
CONSTANT_NameAndType_info {
    u1    tag        
    u2    index    // æŒ‡å‘è¯¥å­—æ®µæˆ–æ–¹æ³•åç§°å¸¸é‡é¡¹çš„ç´¢å¼•
    u2    index    // æŒ‡å‘è¯¥å­—æ®µæˆ–æ–¹æ³•æè¿°ç¬¦å¸¸é‡é¡¹çš„ç´¢å¼•
}
~~~

~~~
0C â€”â€”â€”â€” CONSTANT_NameAndType_info
00 0D â€”â€”â€”â€” è¯¥å­—æ®µæˆ–æ–¹æ³•åç§°å¸¸é‡é¡¹çš„ç´¢å¼•ï¼š13
00 0E â€”â€”â€”â€” è¯¥å­—æ®µæˆ–æ–¹æ³•æè¿°ç¬¦å¸¸é‡é¡¹çš„ç´¢å¼•ï¼š14

#37 = NameAndType        #13:#14        // x:I
~~~

* ç¬¬ä¸‰åå…«ä¸ªå¸¸é‡

~~~
# ç»“æ„
CONSTANT_Utf8_info {
    u1    tag
    u2    length       // UTF-8 ç¼–ç çš„å­—ç¬¦ä¸²é•¿åº¦
    u1    bytes        // é•¿åº¦ä¸º length çš„ UTF-8 ç¼–ç çš„å­—ç¬¦ä¸²
}
~~~

~~~
01 â€”â€”â€”â€” CONSTANT_Utf8_info
00 3C â€”â€”â€”â€” UTF-8 ç¼–ç çš„å­—ç¬¦ä¸²é•¿åº¦ï¼š60
63 6F 6D 2F 62 61 79 65 72 6E 2F 73 68 65 6E 67 73 69 79 75 61 6E 2F 6A 76 6D 5F 6C 65 63 74 75 72 65 2F 62 79 74 65 63 6F 64 65 2F 6C 65 73 73 6F 6E 31 33 2F 4D 79 54 65 73 74 32 â€”â€”â€”â€”  com/bayern/shengsiyuan/jvm_lecture/bytecode/lesson13/MyTest2

#38 = Utf8               com/bayern/shengsiyuan/jvm_lecture/bytecode/lesson13/MyTest2
~~~

* ç¬¬ä¸‰åä¹ä¸ªå¸¸é‡

~~~
# ç»“æ„
CONSTANT_NameAndType_info {
    u1    tag        
    u2    index    // æŒ‡å‘è¯¥å­—æ®µæˆ–æ–¹æ³•åç§°å¸¸é‡é¡¹çš„ç´¢å¼•
    u2    index    // æŒ‡å‘è¯¥å­—æ®µæˆ–æ–¹æ³•æè¿°ç¬¦å¸¸é‡é¡¹çš„ç´¢å¼•
}
~~~

~~~
0C â€”â€”â€”â€” CONSTANT_NameAndType_info
00 1D â€”â€”â€”â€” è¯¥å­—æ®µæˆ–æ–¹æ³•åç§°å¸¸é‡é¡¹çš„ç´¢å¼•ï¼š29
00 1E â€”â€”â€”â€” è¯¥å­—æ®µæˆ–æ–¹æ³•æè¿°ç¬¦å¸¸é‡é¡¹çš„ç´¢å¼•ï¼š30

#39 = NameAndType        #29:#30        // setX:(I)V
~~~

* ç¬¬å››åä¸ªå¸¸é‡

~~~
# ç»“æ„
CONSTANT_Class_info {
    u1    tag
    u2    index    // æŒ‡å‘å…¨é™å®šåå¸¸é‡é¡¹çš„ç´¢å¼•
}
~~~

~~~
07 â€”â€”â€”â€” CONSTANT_Class_info
00 2C â€”â€”â€”â€” å…¨é™å®šåå¸¸é‡é¡¹çš„ç´¢å¼•ï¼š44

#40 = Class              #44            // java/lang/Integer
~~~

* ç¬¬å››åä¸€ä¸ªå¸¸é‡

~~~
# ç»“æ„
CONSTANT_NameAndType_info {
    u1    tag        
    u2    index    // æŒ‡å‘è¯¥å­—æ®µæˆ–æ–¹æ³•åç§°å¸¸é‡é¡¹çš„ç´¢å¼•
    u2    index    // æŒ‡å‘è¯¥å­—æ®µæˆ–æ–¹æ³•æè¿°ç¬¦å¸¸é‡é¡¹çš„ç´¢å¼•
}
~~~

~~~
0C â€”â€”â€”â€” CONSTANT_NameAndType_info
00 2D â€”â€”â€”â€” è¯¥å­—æ®µæˆ–æ–¹æ³•åç§°å¸¸é‡é¡¹çš„ç´¢å¼•ï¼š45
00 2E â€”â€”â€”â€” è¯¥å­—æ®µæˆ–æ–¹æ³•æè¿°ç¬¦å¸¸é‡é¡¹çš„ç´¢å¼•ï¼š46

#41 = NameAndType        #45:#46        // valueOf:(I)Ljava/lang/Integer;
~~~

* ç¬¬å››åäºŒä¸ªå¸¸é‡

~~~
# ç»“æ„
CONSTANT_NameAndType_info {
    u1    tag        
    u2    index    // æŒ‡å‘è¯¥å­—æ®µæˆ–æ–¹æ³•åç§°å¸¸é‡é¡¹çš„ç´¢å¼•
    u2    index    // æŒ‡å‘è¯¥å­—æ®µæˆ–æ–¹æ³•æè¿°ç¬¦å¸¸é‡é¡¹çš„ç´¢å¼•
}
~~~

~~~
0C â€”â€”â€”â€” CONSTANT_NameAndType_info
00 0F â€”â€”â€”â€” è¯¥å­—æ®µæˆ–æ–¹æ³•åç§°å¸¸é‡é¡¹çš„ç´¢å¼•ï¼š15
00 10 â€”â€”â€”â€” è¯¥å­—æ®µæˆ–æ–¹æ³•æè¿°ç¬¦å¸¸é‡é¡¹çš„ç´¢å¼•ï¼š16

#42 = NameAndType        #15:#16        // in:Ljava/lang/Integer;
~~~

* ç¬¬å››åä¸‰ä¸ªå¸¸é‡

~~~
# ç»“æ„
CONSTANT_Utf8_info {
    u1    tag
    u2    length       // UTF-8 ç¼–ç çš„å­—ç¬¦ä¸²é•¿åº¦
    u1    bytes        // é•¿åº¦ä¸º length çš„ UTF-8 ç¼–ç çš„å­—ç¬¦ä¸²
}
~~~

~~~
01 â€”â€”â€”â€” CONSTANT_Utf8_info
00 10 â€”â€”â€”â€” UTF-8 ç¼–ç çš„å­—ç¬¦ä¸²é•¿åº¦ï¼š16
6A 61 76 61 2F 6C 61 6E 67 2F 4F 62 6A 65 63 74 â€”â€”â€”â€” java/lang/Object

#43 = Utf8               java/lang/Object
~~~

* ç¬¬å››åå››ä¸ªå¸¸é‡

~~~
# ç»“æ„
CONSTANT_Utf8_info {
    u1    tag
    u2    length       // UTF-8 ç¼–ç çš„å­—ç¬¦ä¸²é•¿åº¦
    u1    bytes        // é•¿åº¦ä¸º length çš„ UTF-8 ç¼–ç çš„å­—ç¬¦ä¸²
}
~~~

~~~
01 â€”â€”â€”â€” CONSTANT_Utf8_info
00 11 â€”â€”â€”â€” UTF-8 ç¼–ç çš„å­—ç¬¦ä¸²é•¿åº¦ï¼š17
6A 61 76 61 2F 6C 61 6E 67 2F 49 6E 74 65 67 65 72 â€”â€”â€”â€” java/lang/Integer

#44 = Utf8               java/lang/Integer
~~~

* ç¬¬å››åäº”ä¸ªå¸¸é‡

~~~
# ç»“æ„
CONSTANT_Utf8_info {
    u1    tag
    u2    length       // UTF-8 ç¼–ç çš„å­—ç¬¦ä¸²é•¿åº¦
    u1    bytes        // é•¿åº¦ä¸º length çš„ UTF-8 ç¼–ç çš„å­—ç¬¦ä¸²
}
~~~

~~~
01 â€”â€”â€”â€” CONSTANT_Utf8_info
00 07 â€”â€”â€”â€” UTF-8 ç¼–ç çš„å­—ç¬¦ä¸²é•¿åº¦ï¼š7
76 61 6C 75 65 4F 66 â€”â€”â€”â€” valueOf

#45 = Utf8               valueOf
~~~

* ç¬¬å››åå…­ä¸ªå¸¸é‡

~~~
# ç»“æ„
CONSTANT_Utf8_info {
    u1    tag
    u2    length       // UTF-8 ç¼–ç çš„å­—ç¬¦ä¸²é•¿åº¦
    u1    bytes        // é•¿åº¦ä¸º length çš„ UTF-8 ç¼–ç çš„å­—ç¬¦ä¸²
}
~~~

~~~
01 â€”â€”â€”â€” CONSTANT_Utf8_info
00 16 â€”â€”â€”â€” UTF-8 ç¼–ç çš„å­—ç¬¦ä¸²é•¿åº¦ï¼š22
28 49 29 4C 6A 61 76 61 2F 6C 61 6E 67 2F 49 6E 74 65 67 65 72 3B â€”â€”â€”â€” (I)Ljava/lang/Integer;

#46 = Utf8               (I)Ljava/lang/Integer;
~~~

<br>

### å››ï¼Œaccess_flags â€”â€”â€”â€” ç±»çš„è®¿é—®æ§åˆ¶æƒé™
æ ¼å¼ï¼š

~~~
u2    access_flags;
~~~

å†…å®¹ï¼š

~~~
00 21    // ACC_SUPER ä¸ ACC_PUBLIC çš„å¹¶é›†
~~~

<br>

### äº”ï¼Œthis_class â€”â€”â€”â€” ç±»å
æ ¼å¼ï¼š

~~~
u2    this_class
~~~

å†…å®¹ï¼š

~~~
00 05     // å¸¸é‡æ± ä¸­ç´¢å¼•ä¸º 5 çš„å¸¸é‡é¡¹ï¼šCONSTANT_Class_infoï¼Œæœ€ç»ˆæŒ‡å‘ ã€Œ com/bayern/shengsiyuan/jvm_lecture/bytecode/lesson13/MyTest2 ã€
~~~

<br>

### å…­ï¼Œsuper_class â€”â€”â€”â€” çˆ¶ç±»å
æ ¼å¼ï¼š

~~~
u2    super_class
~~~

å†…å®¹ï¼š

~~~
00 0A    // å¸¸é‡æ± ä¸­ç´¢å¼•ä¸º 10 çš„å¸¸é‡é¡¹ï¼šCONSTANT_Class_infoï¼Œæœ€ç»ˆæŒ‡å‘ ã€Œ java/lang/Object ã€
~~~

<br>

### ä¸ƒï¼Œæ¥å£é›†åˆ

#### 7.1 interfaces_count â€”â€”â€”â€” æ¥å£ä¸ªæ•°

~~~
u2    interface_count
~~~

å†…å®¹ï¼š

~~~
00 00    // æ¥å£ä¸ªæ•°ä¸º 0
~~~

<br>

### å…«ï¼Œå­—æ®µé›†åˆ

#### 8.1 fields_count â€”â€”â€”â€” å­—æ®µä¸ªæ•°
æ ¼å¼ï¼š

~~~
u2    fields_count
~~~

å†…å®¹ï¼š

~~~
00 03    // å­—æ®µä¸ªæ•°ä¸º 3
~~~

<br>

#### 8.2 field_info â€”â€”â€”â€” å­—æ®µè¡¨
æ ¼å¼ï¼š

~~~
field_info    fields[fields_count]    // å­—æ®µè¡¨çš„ä¸ªæ•°ä¸º 3
field_info {
    u2    access_flags;
    u2    name_index;
    u2    descriptor_index;
    u2    attributes_count;
    attribute_info    attributes[attributes_count];
}
~~~

å†…å®¹ï¼š

* ç¬¬ä¸€ä¸ªå­—æ®µè¡¨ â€”â€”â€”â€” ã€ŒString strã€

~~~
00 00 â€”â€”â€”â€” access_flagsï¼š-
00 0B â€”â€”â€”â€” name_index ï¼šæŒ‡å‘å¸¸é‡æ± ä¸­ç´¢å¼•ä¸º11çš„å¸¸é‡ï¼Œå¯¹åº”å¸¸é‡ ã€Œ str ã€
00 0C â€”â€”â€”â€” descriptor_index ï¼šæŒ‡å‘å¸¸é‡æ± ä¸­ç´¢å¼•ä¸º12çš„å¸¸é‡ï¼Œå¯¹åº”å¸¸é‡ ã€Œ Ljava/lang/String; ã€
00 00 â€”â€”â€”â€” attributes_count ï¼š0
~~~

* ç¬¬äºŒä¸ªå­—æ®µè¡¨ â€”â€”â€”â€” ã€Œprivate int xã€

~~~
00 02 â€”â€”â€”â€” access_flagsï¼šprivate
00 0D â€”â€”â€”â€” name_index ï¼šæŒ‡å‘å¸¸é‡æ± ä¸­ç´¢å¼•ä¸º13çš„å¸¸é‡ï¼Œå¯¹åº”å¸¸é‡ ã€Œ x ã€
00 0E â€”â€”â€”â€” descriptor_index ï¼šæŒ‡å‘å¸¸é‡æ± ä¸­ç´¢å¼•ä¸º14çš„å¸¸é‡ï¼Œå¯¹åº”å¸¸é‡ ã€Œ I ã€
00 00 â€”â€”â€”â€” attributes_count ï¼š0
~~~

* ç¬¬ä¸‰ä¸ªå­—æ®µè¡¨ â€”â€”â€”â€” ã€Œpublic static Integer inã€

~~~
00 09 â€”â€”â€”â€” access_flagsï¼špublic static
00 0F â€”â€”â€”â€” name_index ï¼šæŒ‡å‘å¸¸é‡æ± ä¸­ç´¢å¼•ä¸º15çš„å¸¸é‡ï¼Œå¯¹åº”å¸¸é‡ ã€Œ in ã€
00 10 â€”â€”â€”â€” descriptor_index ï¼šæŒ‡å‘å¸¸é‡æ± ä¸­ç´¢å¼•ä¸º16çš„å¸¸é‡ï¼Œå¯¹åº”å¸¸é‡ ã€Œ Ljava/lang/Integer; ã€
00 00 â€”â€”â€”â€” attributes_count ï¼š0
~~~

<br>

### ä¹ï¼Œæ–¹æ³•é›†åˆ

#### 9.1 methods_count â€”â€”â€”â€” æ–¹æ³•çš„ä¸ªæ•°
æ ¼å¼ï¼š

~~~
u2    methods_count
~~~

å†…å®¹ï¼š

~~~
00 04     // æ–¹æ³•ä¸ªæ•°ä¸º 4
~~~

#### 9.2 method_info â€”â€”â€”â€” æ–¹æ³•è¡¨
method_info æ•°æ®æ ¼å¼ï¼š

~~~
method_info    methods[methods_count]    // æ–¹æ³•è¡¨çš„ä¸ªæ•°ä¸º 4

method_info {
    u2    access_flags;
    u2    name_index;
    u2    descriptor_index;
    u2    attributes_count;
    attribute_info    attributes[attributes_count];
}

attribute_info {
    u2    attribute_name_index;
    u4    attribute_length;
    u1    info[attribute_length];
}
~~~

<br>
Code å±æ€§æ•°æ®ç»“æ„ï¼š  
Code attribute çš„ä½œç”¨æ˜¯ä¿å­˜è¯¥æ–¹æ³•çš„ç»“æ„ï¼Œå¦‚æ‰€å¯¹åº”çš„å­—èŠ‚ç   

~~~
Code_attribute {
    u2 attribute_name_index;    // å±æ€§åç§°ç´¢å¼•
    u4 attribute_length;        // å±æ€§é•¿åº¦ã€‚ä¸åŒ…æ‹¬â€™attribute_lengthâ€™ã€â€™attribute_name_indexâ€™ã€‚ä¹Ÿå°±ç»§ç»­å¾€ä¸‹ length ä¸ªå­—èŠ‚ã€‚    
    u2 max_stack;               // è¯¥æ–¹æ³•è¿è¡Œçš„ä»»ä½•æ—¶åˆ»æ‰€èƒ½è¾¾åˆ°çš„æ“ä½œæ•°æ ˆçš„æœ€å¤§æ·±åº¦
    u2 max_locals;              // æ–¹æ³•æ‰§è¡ŒæœŸé—´å¯ä»¥åˆ›å»ºçš„æœ€å¤§å±€éƒ¨å˜é‡ä¸ªæ•°
    u4 code_length;             // è¡¨ç¤ºè¯¥æ–¹æ³•æ‰€åŒ…å«çš„å­—èŠ‚ç çš„å­—èŠ‚æ•°
    u1 code[code_length];       // å…·ä½“å­—èŠ‚ç ã€‚å³ï¼Œè¯¥æ–¹æ³•è¢«è°ƒç”¨æ—¶ï¼Œè™šæ‹Ÿæœºæ‰€æ‰§è¡Œçš„å­—èŠ‚ç 
    u2 exception_table_length;    // å¼‚å¸¸è¡¨çš„é•¿åº¦
    {   u2 start_pc;            // start_pc å’Œ end_pc è¡¨ç¤º code æ•°ç»„ä¸­ä» [start_pc, end_pc) å¤„çš„æŒ‡ä»¤æŠ›å‡ºçš„å¼‚å¸¸ä¼šç”±è¿™ä¸ªè¡¨é¡¹æ¥å¤„ç†
        u2 end_pc;
        u2 handler_pc;          // è¡¨ç¤ºå¤„ç†å¼‚å¸¸çš„ä»£ç çš„å¼€å§‹å¤„ã€‚
        u2 catch_type;          // è¡¨ç¤ºä¼šè¢«å¤„ç†çš„å¼‚å¸¸ç±»å‹ï¼Œå®ƒæŒ‡å‘å¸¸é‡æ± é‡Œçš„ä¸€ä¸ªå¼‚å¸¸ç±»ã€‚å½“ catch_type ä¸º 0 æ—¶ï¼Œè¡¨ç¤ºå¤„ç†æ‰€æœ‰çš„å¼‚å¸¸
    } exception_table[exception_table_length];
    u2 attributes_count;
    attribute_info attributes[attributes_count];
}
~~~

<br>

LineNumberTableï¼ˆè¡Œå·è¡¨ï¼‰ï¼š  
è¿™ä¸ªå±æ€§ç”¨æ¥è¡¨ç¤º code æ•°ç»„ä¸­çš„å­—èŠ‚ç å’Œ Java ä»£ç è¡Œæ•°ä¹‹é—´çš„å…³ç³»ã€‚è¿™ä¸ªå±æ€§å¯ä»¥ç”¨æ¥åœ¨è°ƒè¯•çš„æ—¶å€™å®šä½ä»£ç æ‰§è¡Œçš„è¡Œæ•°

~~~
LineNumberTable_attribute {
    u2 attribute_name_index;    // å±æ€§åç§°ç´¢å¼•
    u4 attribute_length;        // å±æ€§é•¿åº¦ã€‚ä¸åŒ…æ‹¬â€™attribute_lengthâ€™ã€â€™attribute_name_indexâ€™ã€‚ä¹Ÿå°±ç»§ç»­å¾€ä¸‹ length ä¸ªå­—èŠ‚ã€‚ 
    u2 line_number_table_length;
    {   u2 start_pc;        // å¯¹äºæŸæºä»£ç æŒ‡ä»¤ï¼Œstart_pcï¼šå¯¹åº”è¯¥æŒ‡ä»¤å¯¹åº”çš„å­—èŠ‚ç ï¼Œåœ¨å…¶å­—èŠ‚ç æ•°ç»„ï¼ˆcode[code_length]ï¼‰ä¸­çš„ç´¢å¼•ï¼›line_numberï¼šå¯¹åº”è¯¥æ‰§è¡Œåœ¨æºç æ–‡ä»¶ä¸­çš„è¡Œæ•°
        u2 line_number;     
    } line_number_table[line_number_table_length];
}
~~~

<br>

LocalVariableTableï¼ˆå±€éƒ¨å˜é‡è¡¨ï¼‰ï¼š

~~~
LocalVariableTable_attribute {
    u2 attribute_name_index;        // å±æ€§åç§°ç´¢å¼•
    u4 attribute_length;            // å±æ€§é•¿åº¦ã€‚ä¸åŒ…æ‹¬â€™attribute_lengthâ€™ã€â€™attribute_name_indexâ€™ã€‚ä¹Ÿå°±ç»§ç»­å¾€ä¸‹ length ä¸ªå­—èŠ‚ã€‚ 
    u2 local_variable_table_length;    // è¡¨ç¤ºâ€™å±€éƒ¨å˜é‡çš„ä¸ªæ•°â€™
    {   u2 start_pc;                // è¡¨ç¤ºå±€éƒ¨å˜é‡çš„å¼€å§‹ä½ç½®
        u2 length;                  // è¡¨ç¤ºå±€éƒ¨å˜é‡çš„é•¿åº¦
        u2 name_index;              // å±€éƒ¨å˜é‡åå­—å¯¹åº”åœ¨å¸¸é‡æ± ä¸­çš„ç´¢å¼•
        u2 descriptor_index;        // å±€éƒ¨å˜é‡æè¿°ç¬¦å¯¹åº”åœ¨å¸¸é‡æ± ä¸­çš„ç´¢å¼•
        u2 index;                   // è¡¨ç¤º indexï¼Œå½“å‰è¿™ä¸ªå±€éƒ¨å˜é‡åœ¨å±€éƒ¨å˜é‡è¡¨æ•°ç»„ä¸­çš„ç´¢å¼•å€¼
    } local_variable_table[local_variable_table_length];
}
~~~

<br>

å†…å®¹ï¼š

* ç¬¬ä¸€ä¸ªæ–¹æ³•è¡¨ â€”â€”â€”â€” æ„é€ æ–¹æ³•

å› ä¸ºæˆ‘ä»¬æ²¡æœ‰æ˜¾ç¤ºçš„å£°æ˜ç±»çš„æ„é€ æ–¹æ³•ï¼Œå› æ­¤è¿™é‡Œæ˜¯ç”± JVM å¸®æˆ‘ä»¬ç”Ÿäº§çš„é»˜è®¤çš„æ„é€ æ–¹æ³•

~~~
00 01 â€”â€”â€”â€” access_flagsï¼špublic
00 11 â€”â€”â€”â€” name_indexï¼šæŒ‡å‘å¸¸é‡æ± ä¸­ç´¢å¼•ä¸º17çš„å¸¸é‡ï¼Œå¯¹åº”å¸¸é‡ã€Œ <init> ã€
00 12 â€”â€”â€”â€” descriptor_indexï¼šæŒ‡å‘å¸¸é‡æ± ä¸­ç´¢å¼•ä¸º18çš„å¸¸é‡ï¼›å¯¹åº”å¸¸é‡ã€Œ ()V ã€
00 01 â€”â€”â€”â€” attributes_countï¼š1
00 13 â€”â€”â€”â€” attribute_name_indexï¼šæŒ‡å‘å¸¸é‡æ± ä¸­ç´¢å¼•ä¸º19çš„å¸¸é‡ï¼Œå¯¹åº”å¸¸é‡ã€Œ Code ã€
00 00 00 42 â€”â€”â€”â€” attribute_lengthï¼š66
00 02 â€”â€”â€”â€” max_stack ï¼šæ“ä½œæ•°æ ˆçš„æœ€å¤§æ·±åº¦ä¸º 2
00 01 â€”â€”â€”â€” max_locals ï¼šå±€éƒ¨å˜é‡çš„æœ€å¤§ä¸ªæ•°ä¸º 1
00 00 00 10 â€”â€”â€”â€” code_length ï¼š16
2A â€”â€”â€”â€” aload_0ï¼›å°†å±€éƒ¨å˜é‡è¡¨ä¸­ç´¢å¼•ä¸º 0 çš„å¼•ç”¨ç±»å‹å˜é‡ï¼ˆå³ï¼Œthis å˜é‡ï¼‰å‹å…¥æ“ä½œæ•°æ ˆä¸­ï¼›
B7 00 01 â€”â€”â€”â€”  invokespecial #1 <java/lang/Object.<init>>ï¼›æ‰§è¡Œå½“å‰ç±»çš„çˆ¶ç±»çš„æ„é€ å‡½æ•°ï¼Œå¯¹çˆ¶ç±»è¿›è¡Œåˆå§‹åŒ–
2A â€”â€”â€”â€” aload_0ï¼›å°†å±€éƒ¨å˜é‡è¡¨ä¸­ç´¢å¼•ä¸º 0 çš„å¼•ç”¨ç±»å‹å˜é‡ï¼ˆå³ï¼Œthis å˜é‡ï¼‰å‹å…¥æ“ä½œæ•°æ ˆä¸­ï¼›ï¼ˆä¹‹å‰å‹å…¥æ“ä½œæ•°æ ˆçš„ this å˜é‡å·²ç»åœ¨æ‰§è¡Œ invokespecial çš„æ—¶å€™å¼¹å‡ºæ ˆä½œä¸º invokespecial æ‰§è¡Œçš„å‚æ•°ä½¿ç”¨äº†ï¼‰
12 02 â€”â€”â€”â€” ldc #2 <Welcome> ï¼›å°†å¸¸é‡æ± ä¸­çš„ã€ŒWelcomeã€å­—ç¬¦ä¸²å‹å…¥æ“ä½œæ•°æ ˆé¡¶
B5 00 03 â€”â€”â€”â€”  putfield #3 <com/bayern/shengsiyuan/jvm_lecture/bytecode/lesson13/MyTest2.str>ï¼›è®¾ç½®ã€ŒString strã€å­—æ®µçš„å€¼ä¸ºã€ŒWelcomeã€
2A â€”â€”â€”â€” aload_0ï¼›å°†å±€éƒ¨å˜é‡è¡¨ä¸­ç´¢å¼•ä¸º 0 çš„å¼•ç”¨ç±»å‹å˜é‡ï¼ˆå³ï¼Œthis å˜é‡ï¼‰å‹å…¥æ“ä½œæ•°æ ˆä¸­
08 â€”â€”â€”â€” iconst_5ï¼›å°†æ•´æ•°å¸¸é‡å€¼ 5 å‹å…¥æ“ä½œæ•°æ ˆé¡¶
B5 00 04 â€”â€”â€”â€”  putfield #4  <com/bayern/shengsiyuan/jvm_lecture/bytecode/lesson13/MyTest2.x>ï¼›ï¼›è®¾ç½®ã€Œprivate int xã€å­—æ®µçš„å€¼ä¸ºã€Œ5ã€
B1 â€”â€”â€”â€” returnï¼›æ–¹æ³•ç»“æŸè¿”å›
00 00 â€”â€”â€”â€” exception_table_length ï¼š0
00 02 â€”â€”â€”â€” attributes_count ï¼š2
00 14 â€”â€”â€”â€” attribute_name_indexï¼šæŒ‡å‘å¸¸é‡æ± ä¸­ç´¢å¼•ä¸º20çš„å¸¸é‡ï¼Œå¯¹åº”å¸¸é‡ã€Œ LineNumberTable ã€
00 00 00 0E â€”â€”â€”â€” attribute_lengthï¼š14
00 03 â€”â€”â€”â€” line_number_table_length ï¼š3
00 00 00 03 â€”â€”â€”â€” start_pcï¼š0ï¼›line_numberï¼š3ï¼›ä» code[0]å¼€å§‹çš„å­—èŠ‚ç æŒ‡ä»¤ï¼ˆå³ï¼Œ2Aï¼‰å¯¹åº”äº Java æºä»£ç æ˜¯è¡Œå· 3 çš„ Java ä»£ç 
00 04 00 04 â€”â€”â€”â€” start_pcï¼š4ï¼›line_numberï¼š4
00 0A 00 06 â€”â€”â€”â€” start_pcï¼š10ï¼›line_numberï¼š6
00 15 â€”â€”â€”â€” attribute_name_indexï¼šæŒ‡å‘å¸¸é‡æ± ä¸­ç´¢å¼•ä¸º21çš„å¸¸é‡ï¼Œå¯¹åº”å¸¸é‡ã€Œ LocalVariableTable ã€
00 00 00 0C â€”â€”â€”â€” attribute_lengthï¼š12
00 01 â€”â€”â€”â€” local_variable_table_length ï¼š1
00 00 â€”â€”â€”â€” start_pc ï¼š0 
00 10 â€”â€”â€”â€” length ï¼š16 ï¼›æŒ‡è¿™ä¸ªå±€éƒ¨å˜é‡çš„å¤„åœ¨ code æ•°ç»„çš„[start_pc, start_pc + lenght) ç´¢å¼•èŒƒå›´å†…ã€‚   
00 16 â€”â€”â€”â€” name_indexï¼šæŒ‡å‘å¸¸é‡æ± ä¸­ç´¢å¼•ä¸º22çš„å¸¸é‡ï¼Œå¯¹åº”å¸¸é‡ã€Œ this ã€
00 17 â€”â€”â€”â€” descriptor_indexï¼šæŒ‡å‘å¸¸é‡æ± ä¸­ç´¢å¼•ä¸º23çš„å¸¸é‡ï¼Œå¯¹åº”å¸¸é‡ã€Œ Lcom/bayern/shengsiyuan/jvm_lecture/bytecode/lesson13/MyTest2; ã€
00 00 â€”â€”â€”â€” indexï¼š0
~~~

> `ğŸ‘†å†æ¬¡è¯´æ˜ï¼Œç±»çš„æˆå‘˜å˜é‡æ˜¯åœ¨æ„é€ æ–¹æ³•ä¸­å®ç°çœŸæ­£çš„èµ‹å€¼çš„ï¼`

<br>

* ç¬¬äºŒä¸ªæ–¹æ³• â€”â€”â€”â€” ã€Œpublic static void main(String[] args) ã€

~~~
00 09 â€”â€”â€”â€” access_flagsï¼špublic static
00 18 â€”â€”â€”â€” name_indexï¼šæŒ‡å‘å¸¸é‡æ± ä¸­ç´¢å¼•ä¸º24çš„å¸¸é‡ï¼›å¯¹åº”å¸¸é‡ã€Œ main ã€ 
00 19 â€”â€”â€”â€” descriptor_indexï¼šæŒ‡å‘å¸¸é‡æ± ä¸­ç´¢å¼•ä¸º25çš„å¸¸é‡ï¼Œå¯¹åº”å¸¸é‡ã€Œ ([Ljava/lang/String;)V ã€
00 01 â€”â€”â€”â€” attributes_countï¼š1 
00 13 â€”â€”â€”â€” attribute_name_indexï¼šæŒ‡å‘å¸¸é‡æ± ä¸­ç´¢å¼•ä¸º19çš„å¸¸é‡ï¼Œå¯¹åº”å¸¸é‡ã€Œ Code ã€ 
00 00 00 57 â€”â€”â€”â€” attribute_lengthï¼š87
00 02 â€”â€”â€”â€” max_stack ï¼šæ“ä½œæ•°æ ˆçš„æœ€å¤§æ·±åº¦ä¸º 2
00 02 â€”â€”â€”â€” max_locals ï¼šå±€éƒ¨å˜é‡çš„æœ€å¤§ä¸ªæ•°ä¸º 2
00 00 00 17 â€”â€”â€”â€” code_length ï¼š23
BB 00 05 â€”â€”â€”â€”  new #5 <com/bayern/shengsiyuan/jvm_lecture/bytecode/lesson13/MyTest2>ï¼›åˆ›å»ºä¸€ä¸ª MyTest2 å¯¹è±¡ï¼ˆåˆ†é…äº†å†…å­˜ï¼Œå¹¶å°†å®ä¾‹å˜é‡è¿›è¡Œäº†é»˜è®¤åˆå§‹åŒ–ï¼Œå³ï¼Œå®ä¾‹å˜é‡çš„å€¼éƒ½ä¸ºé»˜è®¤å€¼ï¼Œè€Œéæˆ‘ä»¬å®šä¹‰çš„çœŸæ˜¯å€¼ï¼‰ï¼Œå¹¶å°†å¯¹è±¡å¼•ç”¨å‹å…¥æ ˆé¡¶
59 â€”â€”â€”â€” dupï¼›æ‹·è´æ ˆé¡¶å…ƒç´ ï¼Œå°†æ‹·è´çš„å…ƒç´ å‹å…¥æ ˆé¡¶
B7 00 06 â€”â€”â€”â€”  invokespecial #6 <com/bayern/shengsiyuan/jvm_lecture/bytecode/lesson13/MyTest2.<init>>ï¼›æ‰§è¡Œ MyTest2 ç±»çš„æ„é€ æ–¹æ³•ã€‚
4C â€”â€”â€”â€” astore_1ï¼›å°†æ ˆé¡¶å…ƒç´ å¼¹å‡ºï¼ˆå³ï¼ŒmyTest2 å¯¹è±¡å¼•ç”¨ï¼‰ï¼Œæ”¾å…¥å±€éƒ¨å˜é‡è¡¨ç´¢å¼•ä¸º 1 çš„ slot ä¸­ã€‚
2B â€”â€”â€”â€” aload_1ï¼›å°†å±€éƒ¨å˜é‡è¡¨ä¸­ç´¢å¼•ä¸º 1 çš„å˜é‡ï¼ˆå³ï¼ŒmyTest2 å¯¹è±¡å¼•ç”¨ï¼‰å‹å…¥æ“ä½œæ•°æ ˆä¸­ï¼›
10 08 â€”â€”â€”â€” bipush 8ï¼›å°†æ•°å€¼ 8 å‹å…¥æ“ä½œæ•°æ ˆé¡¶
B6 00 07 â€”â€”â€”â€”  invokevirtual #7 <com/bayern/shengsiyuan/jvm_lecture/bytecode/lesson13/MyTest2.setX>ï¼›æ‰§è¡Œã€ŒmyTest2.setX(8);ã€æ–¹æ³•
10 14 â€”â€”â€”â€” bipush 20ï¼›å°†æ•°å€¼ 20 å‹å…¥æ“ä½œæ•°æ ˆé¡¶
B8 00 08 â€”â€”â€”â€”  invokestatic #8 <java/lang/Integer.valueOf>ï¼›æ‰§è¡Œè‡ªåŠ¨è£…ç®±æ“ä½œï¼Œå°†æ•°å€¼ 20 è½¬åŒ–ä¸º Integer å¯¹è±¡ï¼Œå¹¶å°†è¿™ä¸ª Integer å¯¹è±¡å‹å…¥æ“ä½œæ•°æ ˆ
B3 00 09 â€”â€”â€”â€”  putstatic #9 <com/bayern/shengsiyuan/jvm_lecture/bytecode/lesson13/MyTest2.in>ï¼›å°†ã€Œ20å°è£…çš„ Integer å¯¹è±¡ï¼ˆé€šè¿‡å¼¹å‡ºæ“ä½œæ•°æ ˆæ ˆé¡¶å…ƒç´ å¾—åˆ°ï¼‰ã€èµ‹å€¼ç»™é™æ€å˜é‡ã€Œpublic static Integer inã€
B1 â€”â€” returnï¼›æ–¹æ³•ç»“æŸè¿”å›
00 00 â€”â€”â€”â€” exception_table_length ï¼š0
00 02 â€”â€”â€”â€” attributes_count ï¼š2
00 14 â€”â€”â€”â€” attribute_name_indexï¼šæŒ‡å‘å¸¸é‡æ± ä¸­ç´¢å¼•ä¸º20çš„å¸¸é‡ï¼Œå¯¹åº”å¸¸é‡ã€Œ LineNumberTable ã€
00 00 00 12 â€”â€”â€”â€” attribute_lengthï¼š18
00 04 â€”â€”â€”â€” line_number_table_length ï¼š4
00 00 00 0B â€”â€”â€”â€” start_pcï¼š0ï¼›line_numberï¼š11
00 08 00 0D â€”â€”â€”â€” start_pcï¼š8ï¼›line_numberï¼š13
00 0E 00 0F â€”â€”â€”â€” start_pcï¼š14ï¼›line_numberï¼š15
00 16 00 10 â€”â€”â€”â€” start_pcï¼š22ï¼›line_numberï¼š16
00 15 â€”â€”â€”â€” attribute_name_indexï¼šæŒ‡å‘å¸¸é‡æ± ä¸­ç´¢å¼•ä¸º21çš„å¸¸é‡ï¼Œå¯¹åº”å¸¸é‡ã€Œ LocalVariableTable ã€
00 00 00 16 â€”â€”â€”â€” attribute_lengthï¼š22
00 02 â€”â€”â€”â€” local_variable_table_length ï¼š2
00 00 â€”â€”â€”â€” start_pc ï¼š0
00 17 â€”â€”â€”â€” length ï¼š23
00 1A â€”â€”â€”â€” name_indexï¼šæŒ‡å‘å¸¸é‡æ± ä¸­ç´¢å¼•ä¸º26çš„å¸¸é‡ï¼Œå¯¹åº”å¸¸é‡ã€Œ args ã€
00 1B â€”â€”â€”â€” descriptor_indexï¼šå¯¹åº”å¸¸é‡ã€Œ [Ljava/lang/String; ã€
00 00 â€”â€”â€”â€” indexï¼š0ï¼ˆåœ¨ LocalVariableTable ä¸­çš„ç´¢å¼•ï¼‰
00 08 â€”â€”â€”â€” start_pc ï¼š8
00 0F â€”â€”â€”â€” length ï¼š15
00 1C â€”â€”â€”â€” name_indexï¼šæŒ‡å‘å¸¸é‡æ± ä¸­ç´¢å¼•ä¸º28çš„å¸¸é‡ï¼Œå¯¹åº”å¸¸é‡ã€Œ myTest2 ã€
00 17 â€”â€”â€”â€” descriptor_indexï¼šå¯¹åº”å¸¸é‡ã€Œ Lcom/bayern/shengsiyuan/jvm_lecture/bytecode/lesson13/MyTest2; ã€
00 01 â€”â€”â€”â€” indexï¼š1ï¼ˆåœ¨ LocalVariableTable ä¸­çš„ç´¢å¼•ï¼‰
~~~

ã€ŒMyTest2 myTest2 = new MyTest2();ã€æ“ä½œå®é™…ä¸Šå®Œæˆäº† 3 ä»¶äº‹æƒ…ï¼š  
â‘  ä¸ºè¿™ä¸ªå¯¹è±¡åœ¨å†…å­˜ï¼Œä¹Ÿå°±æ˜¯åœ¨å †ä¸Šå¼€è¾Ÿä¸€ä¸ªå†…å­˜ç©ºé—´

~~~
BB 00 05 â€”â€”â€”â€”  new #5 <com/bayern/shengsiyuan/jvm_lecture/bytecode/lesson13/MyTest2>ï¼›åˆ›å»ºä¸€ä¸ª MyTest2 å¯¹è±¡ï¼ˆåˆ†é…äº†å†…å­˜ï¼Œå¹¶å°†å®ä¾‹å˜é‡è¿›è¡Œäº†é»˜è®¤åˆå§‹åŒ–ï¼Œå³ï¼Œå®ä¾‹å˜é‡çš„å€¼éƒ½ä¸ºé»˜è®¤å€¼ï¼Œè€Œéæˆ‘ä»¬å®šä¹‰çš„çœŸæ˜¯å€¼ï¼‰ï¼Œå¹¶å°†å¯¹è±¡å¼•ç”¨å‹å…¥æ ˆé¡¶
59 â€”â€”â€”â€” dupï¼›æ‹·è´æ ˆé¡¶å…ƒç´ ï¼Œå°†æ‹·è´çš„å…ƒç´ å‹å…¥æ ˆé¡¶ï¼›ç”¨äºä¸‹ä¸€æ­¥ã€Œinvokespecialã€æŒ‡ä»¤çš„ç¬¬äºŒä¸ªå‚æ•°ä¼ å…¥ã€‚
~~~

â‘¡ æ‰§è¡Œæ„é€ æ–¹æ³•

~~~
B7 00 06 â€”â€”â€”â€”  invokespecial #6 <com/bayern/shengsiyuan/jvm_lecture/bytecode/lesson13/MyTest2.<init>>ï¼›æ‰§è¡Œ MyTest2 ç±»çš„æ„é€ æ–¹æ³•ã€‚ã€Œinvokespecialã€æŒ‡ä»¤çš„ç¬¬ä¸€ä¸ªå‚æ•°æ˜¯ç¬¦å·å¼•ç”¨â€˜<com/bayern/shengsiyuan/jvm_lecture/bytecode/lesson13/MyTest2.<init>>â€™ï¼Œç¬¬äºŒä¸ªå‚æ•°æ˜¯ï¼Œæ“ä½œæ•°æ ˆé¡¶çš„å…ƒç´ ï¼ˆğŸ‘ˆæ³¨æ„ï¼Œè¿™é‡Œæ¶‰åŠåˆ°å¼¹æ ˆæ“ä½œã€‚æ‰€ä»¥æ‰æœ‰äº†ğŸ‘†ä¸€æ­¥çš„å°†æ“ä½œæ•°æ ˆé¡¶çš„å…ƒç´ æ‹·è´ä¸€ä»½ï¼Œå¹¶ä¸”å‹å…¥æ“ä½œæ•°æ ˆä¸­ï¼‰ã€‚
~~~

â‘¢ å°†æ„é€ æ–¹æ³•æ‰§è¡Œå®Œåï¼Œè¿”å›çš„å…¶åœ¨å †ä¸Šæ‰€ç”Ÿæˆçš„è¯¥å¯¹è±¡çš„å¼•ç”¨å€¼è¿”å›

~~~
4C â€”â€”â€”â€” astore_1ï¼›å°†æ ˆé¡¶å…ƒç´ å¼¹å‡ºï¼ˆå³ï¼ŒmyTest2 å¯¹è±¡å¼•ç”¨ï¼‰ï¼Œæ”¾å…¥å±€éƒ¨å˜é‡è¡¨ç´¢å¼•ä¸º 1 çš„ slot ä¸­ã€‚
~~~

<br>

* ç¬¬ä¸‰ä¸ªæ–¹æ³• â€”â€”â€”â€” ã€Œpublic void setX(int x)ã€

~~~
00 01 â€”â€”â€”â€” access_flagsï¼špublic
00 1D â€”â€”â€”â€” name_indexï¼šæŒ‡å‘å¸¸é‡æ± ä¸­ç´¢å¼•ä¸º29çš„å¸¸é‡ï¼Œå¯¹åº”å¸¸é‡ã€Œ setX ã€
00 1E â€”â€”â€”â€” descriptor_indexï¼šæŒ‡å‘å¸¸é‡æ± ä¸­ç´¢å¼•ä¸º30çš„å¸¸é‡ï¼Œå¯¹åº”å¸¸é‡ã€Œ (I)V ã€
00 01 â€”â€”â€”â€” attributes_countï¼š1
00 13 â€”â€”â€”â€” attribute_name_indexï¼šæŒ‡å‘å¸¸é‡æ± ä¸­ç´¢å¼•ä¸º19çš„å¸¸é‡ï¼Œå¯¹åº”å¸¸é‡ã€Œ Code ã€
00 00 00 3E â€”â€”â€”â€” attribute_lengthï¼š62
00 02 â€”â€”â€”â€” max_stack ï¼šæ“ä½œæ•°æ ˆçš„æœ€å¤§æ·±åº¦ä¸º 2
00 02 â€”â€”â€”â€” max_locals ï¼šå±€éƒ¨å˜é‡çš„æœ€å¤§ä¸ªæ•°ä¸º 2
00 00 00 06 â€”â€”â€”â€” code_length ï¼š6
2A â€”â€”â€”â€” aload_0ï¼›å°†å±€éƒ¨å˜é‡è¡¨ä¸­ç´¢å¼•ä¸º 0 çš„å¼•ç”¨ç±»å‹å˜é‡ï¼ˆå³ï¼Œthis å˜é‡ï¼‰å‹å…¥æ“ä½œæ•°æ ˆä¸­ï¼›
1B â€”â€”â€”â€” iload_1ï¼›å°†å±€éƒ¨å˜é‡è¡¨ä¸­ç´¢å¼•ä¸º 1 çš„ int ç±»å‹å˜é‡ï¼ˆå³ï¼Œthis å˜é‡ï¼‰å‹å…¥æ“ä½œæ•°æ ˆä¸­ï¼›
B5 00 04 â€”â€”â€”â€” putfield #4 <com/bayern/shengsiyuan/jvm_lecture/bytecode/lesson13/MyTest2.x>ï¼›è®¾ç½® this çš„æˆå‘˜å˜é‡ x çš„å€¼ä¸ºæ–¹æ³•ä¼ å…¥å‚æ•° xã€‚å› ä¸º JVM çš„å­—èŠ‚ç æ˜¯åŸºäºæ“ä½œæ•°æ ˆæ‰§è¡Œçš„ã€‚å› æ­¤ï¼Œè¿™é‡Œçš„ this å¯¹è±¡å’Œæ–¹æ³•å‚æ•° x éƒ½æ˜¯é€šè¿‡æ“ä½œæ•°æ ˆå¾—åˆ°çš„ï¼Œæ‰€ä»¥æˆ‘ä»¬æ€»æ˜¯å…ˆå°†æ•°æ®å‹å…¥æ ˆä¸­ï¼Œåœ¨æŒ‡ä»¤æ‰§è¡Œçš„æ—¶å€™ä¼šé€šè¿‡å¼¹æ ˆæ¥è·å–æ‰€éœ€çš„æ•°æ®ã€‚
B1 â€”â€”â€”â€” returnï¼›æ–¹æ³•ç»“æŸè¿”å›
00 00 â€”â€”â€”â€” exception_table_length ï¼š0
00 02 â€”â€”â€”â€” attributes_count ï¼š2
00 14 â€”â€”â€”â€” attribute_name_indexï¼šæŒ‡å‘å¸¸é‡æ± ä¸­ç´¢å¼•ä¸º20çš„å¸¸é‡ï¼Œå¯¹åº”å¸¸é‡ã€Œ LineNumberTable ã€
00 00 00 0A â€”â€”â€”â€” attribute_lengthï¼š10
00 02 â€”â€”â€”â€” line_number_table_length ï¼š2
00 00 00 13 â€”â€”â€”â€” start_pcï¼š0ï¼›line_numberï¼š19
00 05 00 14 â€”â€”â€”â€” start_pcï¼š5ï¼›line_numberï¼š20
00 15 â€”â€”â€”â€” attribute_name_indexï¼šæŒ‡å‘å¸¸é‡æ± ä¸­ç´¢å¼•ä¸º21çš„å¸¸é‡ï¼Œå¯¹åº”å¸¸é‡ã€Œ LocalVariableTable ã€
00 00 00 16 â€”â€”â€”â€” attribute_lengthï¼š22
00 02 â€”â€”â€”â€” local_variable_table_length ï¼š2
00 00 â€”â€”â€”â€” start_pc ï¼š0
00 06 â€”â€”â€”â€” length ï¼š6
00 16 â€”â€”â€”â€” name_indexï¼šæŒ‡å‘å¸¸é‡æ± ä¸­ç´¢å¼•ä¸º22çš„å¸¸é‡ï¼Œå¯¹åº”å¸¸é‡ã€Œ this ã€
00 17 â€”â€”â€”â€” descriptor_indexï¼šæŒ‡å‘å¸¸é‡æ± ä¸­ç´¢å¼•ä¸º23çš„å¸¸é‡ï¼Œå¯¹åº”å¸¸é‡ã€Œ Lcom/bayern/shengsiyuan/jvm_lecture/bytecode/lesson13/MyTest2; ã€
00 00 â€”â€”â€”â€” indexï¼š0ï¼ˆåœ¨ LocalVariableTable ä¸­çš„ç´¢å¼•ï¼‰
00 00 â€”â€”â€”â€” start_pc ï¼š0
00 06 â€”â€”â€”â€” length ï¼š6
00 0D â€”â€”â€”â€” name_indexï¼šæŒ‡å‘å¸¸é‡æ± ä¸­ç´¢å¼•ä¸º13çš„å¸¸é‡ï¼Œå¯¹åº”å¸¸é‡ã€Œ x ã€
00 0E â€”â€”â€”â€” descriptor_indexï¼šæŒ‡å‘å¸¸é‡æ± ä¸­ç´¢å¼•ä¸º14çš„å¸¸é‡ï¼Œå¯¹åº”å¸¸é‡ã€Œ I ã€
00 01 â€”â€”â€”â€” indexï¼š1ï¼ˆåœ¨ LocalVariableTable ä¸­çš„ç´¢å¼•ï¼‰
~~~

æ³¨æ„ï¼Œã€Œpublic void setX(int x)ã€æ–¹æ³•çš„ã€Œargs_size=2ã€ã€‚  
å¯¹äº Java ç±»ä¸­çš„æ¯ä¸€ä¸ªå®ä¾‹æ–¹æ³•ï¼ˆé static æ–¹æ³•ï¼‰ï¼Œå…¶åœ¨ç¼–è¯‘åæ‰€ç”Ÿäº§çš„å­—èŠ‚ç å½“ä¸­ï¼Œæ–¹æ³•å‚æ•°çš„æ•°é‡æ€»æ˜¯ä¼šæ¯”æºä»£ç ä¸­æ–¹æ³•å‚æ•°çš„æ•°é‡å¤šä¸€ä¸ªï¼ˆthisï¼‰ï¼Œå®ƒä½äºæ–¹æ³•çš„ç¬¬ä¸€ä¸ªå‚æ•°ä½ç½®å¤„ï¼›è¿™æ ·ï¼Œæˆ‘ä»¬å°±å¯ä»¥åœ¨ Java çš„å®ä¾‹æ–¹æ³•ä¸­ä½¿ç”¨ this æ¥å»è®¿é—®å½“å‰å¯¹è±¡çš„å±æ€§ä»¥åŠå…¶ä»–æ–¹æ³•ã€‚

è¿™ä¸ªæ“ä½œæ˜¯åœ¨ç¼–è¯‘æœŸé—´å®Œæˆçš„ï¼Œå³ï¼Œç”± javac ç¼–è¯‘å™¨åœ¨ç¼–è¯‘çš„æ—¶å€™å°†å¯¹ this çš„è®¿é—®è½¬åŒ–ä¸ºå¯¹ä¸€ä¸ªæ™®é€šå®ä¾‹æ–¹æ³•å‚æ•°çš„è®¿é—®ï¼›æ¥ä¸‹æ¥åœ¨è¿è¡ŒæœŸé—´ï¼Œç”± JVM åœ¨è°ƒç”¨å®ä¾‹æ–¹æ³•æ—¶ï¼Œè‡ªåŠ¨å‘å®ä¾‹æ–¹æ³•ä¼ å…¥è¯¥ this å‚æ•°ã€‚æ‰€ä»¥ï¼Œåœ¨å®ä¾‹æ–¹æ³•çš„å±€éƒ¨å˜é‡è¡¨ä¸­ï¼Œè‡³å°‘ä¼šæœ‰ä¸€ä¸ªæŒ‡å‘å½“å‰å¯¹è±¡çš„å±€éƒ¨å˜é‡ã€‚

<br>

* ç¬¬å››ä¸ªæ–¹æ³• â€”â€”â€”â€” ç±»åˆå§‹åŒ–æ–¹æ³•<clinit>

~~~
00 08 â€”â€”â€”â€” access_flagsï¼šstatic
00 1F â€”â€”â€”â€” name_indexï¼šæŒ‡å‘å¸¸é‡æ± ä¸­ç´¢å¼•ä¸º31çš„å¸¸é‡ï¼Œå¯¹åº”å¸¸é‡ã€Œ <clinit> ã€
00 12 â€”â€”â€”â€” descriptor_indexï¼šæŒ‡å‘å¸¸é‡æ± ä¸­ç´¢å¼•ä¸º18çš„å¸¸é‡ï¼Œå¯¹åº”å¸¸é‡ã€Œ ()V ã€ 
00 01 â€”â€”â€”â€” attributes_countï¼š1
00 13 â€”â€”â€”â€” attribute_name_indexï¼šæŒ‡å‘å¸¸é‡æ± ä¸­ç´¢å¼•ä¸º19çš„å¸¸é‡ï¼Œå¯¹åº”å¸¸é‡ã€Œ Code ã€
00 00 00 21  â€”â€”â€”â€” attribute_lengthï¼š33
00 01 â€”â€”â€”â€” max_stack ï¼šæ“ä½œæ•°æ ˆçš„æœ€å¤§æ·±åº¦ä¸º 1
00 00 â€”â€”â€”â€” max_locals ï¼šå±€éƒ¨å˜é‡çš„æœ€å¤§ä¸ªæ•°ä¸º 0
00 00 00 09 â€”â€”â€”â€” code_length ï¼š9
10 0A â€”â€”â€”â€” bipush 10ï¼›å°†æ•°å€¼ 10 å‹å…¥æ“ä½œæ•°æ ˆé¡¶
B8 00 08 â€”â€”â€”â€” invokestatic #14 <java/lang/Integer.valueOf>ï¼›ï¼›æ‰§è¡Œè‡ªåŠ¨è£…ç®±æ“ä½œï¼Œå°†æ•°å€¼ 10 è½¬åŒ–ä¸º Integer å¯¹è±¡ï¼Œå¹¶å°†è¿™ä¸ª Integer å¯¹è±¡å‹å…¥æ“ä½œæ•°æ ˆ
B3 00 09 â€”â€”â€”â€” putstatic #15 <com/bayern/shengsiyuan/jvm_lecture/bytecode/MyTest2.in>ï¼›å°†ã€Œ10å°è£…çš„ Integer å¯¹è±¡ï¼ˆé€šè¿‡å¼¹å‡ºæ“ä½œæ•°æ ˆæ ˆé¡¶å…ƒç´ å¾—åˆ°ï¼‰ã€èµ‹å€¼ç»™ç±»çš„é™æ€å˜é‡ã€Œpublic static Integer inã€
B1 â€”â€”â€”â€” returnï¼›æ–¹æ³•ç»“æŸè¿”å›
00 00 â€”â€”â€”â€” exception_table_length ï¼š0
00 01 â€”â€”â€”â€” attributes_count ï¼š1
00 14 â€”â€”â€”â€” attribute_name_indexï¼šæŒ‡å‘å¸¸é‡æ± ä¸­ç´¢å¼•ä¸º20çš„å¸¸é‡ï¼Œå¯¹åº”å¸¸é‡ã€Œ LineNumberTable ã€
00 00 00 06 â€”â€”â€”â€” attribute_lengthï¼š6
00 01 â€”â€”â€”â€” line_number_table_length ï¼š1
00 00 00 08 â€”â€”â€”â€” start_pcï¼š0ï¼›line_numberï¼š8
~~~
ğŸ‘†é™æ€å˜é‡çš„èµ‹å€¼å°±åœ¨ clinit ä¸­

<br>

### åï¼Œå±æ€§é›†åˆ
#### 10.1 attributes_count â€”â€”â€”â€” é™„åŠ å±æ€§çš„ä¸ªæ•°
æ ¼å¼ï¼š

~~~
u2    attributes_count;
~~~

å†…å®¹ï¼š

~~~
00 01    // é™„åŠ å±æ€§çš„ä¸ªæ•°ä¸º 1
~~~

<br>

#### 10.2 attributes â€”â€”â€”â€” é™„åŠ å±æ€§è¡¨

æ ¼å¼ï¼š

~~~
attribute_info    attributes[attributes_count];
attribute_info {
    u2    attribute_name_index;
    u4    attribute_length;
    u1    info[attribute_length];
}
SourceFile_attribute {
    u2 attribute_name_index;
    u4 attribute_length;
    u2 sourcefile_index;
}
~~~

å†…å®¹ï¼š

~~~
00 20 â€”â€”â€”â€” attribute_name_indexï¼šå¯¹åº”å¸¸é‡ã€Œ SourceFile ã€
00 00 00 02 â€”â€”â€”â€” attribute_lengthï¼š2
00 21 â€”â€”â€”â€” sourcefile_indexï¼šå¯¹åº”å¸¸é‡ã€Œ MyTest2.java ã€
~~~











































